{"eventpn": [72, 72], "eventspan": [20, 71], "allspan": [[20, 71], [46, 70], [53, 70]], "id": "2134.txt", "doc": "『 伙 伴 关 系 』 的 潜 台 词\n本 报 驻 美 国 记 者 李 云 飞\n美 国 总 统 克 林 顿 与 爱 沙 尼 亚 、 拉 脱 维 亚 和 立 陶 宛 三 国 总 统 ， 今 天 在 白 宫 正 式 签 署 美 国 与 波 罗 的 海 三 国 的 伙 伴 关 系 宪 章 。\n这 是 美 国 加 强 与 波 罗 的 海 三 国 关 系 的 新 的 引 人 注 目 行 动 。\n宪 章 的 主 要 内 容 是 ， 美 国 承 诺 对 波 罗 的 海 三 国 的 独 立 、 主 权 和 领 土 完 整 给 予 道 义 上 和 政 治 上 的 支 持 。\n美 国 还 表 明 ， 波 罗 的 海 三 国 在 条 件 成 熟 时 加 入 北 约 “ 有 利 于 欧 洲 的 稳 定 和 北 约 的 战 略 目 标 ” 。\n根 据 这 个 宪 章 的 精 神 ， 将 成 立 美 国 、 爱 沙 尼 亚 、 拉 脱 维 亚 和 立 陶 宛 的 四 方 “ 伙 伴 关 系 委 员 会 ” ， 由 美 国 副 国 务 卿 塔 尔 博 特 主 持 。\n还 将 成 立 若 干 经 济 发 展 的 工 作 小 组 ， 类 似 这 些 小 组 的 防 务 小 组 已 经 成 立 。\n克 林 顿 总 统 今 天 还 宣 布 建 立 １ ５ ０ ０ 万 美 元 的 波 罗 的 海 三 国 与 美 国 伙 伴 关 系 基 金 。\n宪 章 中 最 关 键 和 敏 感 的 部 分 是 ， 美 国 将 促 进 波 罗 的 海 三 国 加 入 北 约 ， 并 支 持 它 们 在 这 方 面 所 做 的 努 力 。\n此 间 舆 论 认 为 ， 这 表 明 美 国 对 未 来 欧 洲 防 务 的 计 划 不 只 限 于 北 约 的 第 一 轮 东 扩 。\n美 国 所 担 心 的 只 是 怕 因 此 引 起 俄 罗 斯 的 反 对 。\n实 际 上 ， 俄 罗 斯 早 已 明 确 表 示 ， 北 约 不 能 东 扩 到 波 罗 的 海 三 国 。\n俄 罗 斯 总 理 切 尔 诺 梅 尔 金 去 年 ７ 月 、 总 统 叶 利 钦 去 年 下 半 年 先 后 两 次 提 出 ， 只 要 波 罗 的 海 三 国 不 加 入 北 约 ， 俄 罗 斯 愿 意 与 北 约 及 西 方 国 家 一 起 为 这 三 国 提 供 “ 联 合 安 全 保 障 ” 。\n不 仅 俄 罗 斯 ， 美 国 的 北 约 盟 国 对 波 罗 的 海 三 国 加 入 也 持 有 很 大 的 保 留 。\n它 们 坚 持 认 为 ， 波 罗 的 海 三 国 加 入 北 约 不 仅 要 等 到 它 们 本 身 条 件 成 熟 的 时 候 ， 而 且 还 要 符 合 所 有 盟 国 的 整 体 战 略 利 益 。\n一 位 北 约 官 员 说 得 更 明 确 ， 这 在 很 大 程 度 上 取 决 于 波 罗 的 海 三 国 与 俄 罗 斯 关 系 的 改 善 。\n因 此 ， 这 个 宪 章 的 签 署 整 整 谈 了 一 年 的 时 间 ， 宪 章 关 于 这 三 国 加 入 北 约 的 问 题 ， 只 是 表 明 一 种 意 向 ， 实 际 上 在 可 预 见 的 将 来 不 会 提 出 来 。\n舆 论 认 为 ， 这 是 考 虑 到 有 关 各 方 的 态 度 ， 权 衡 利 弊 后 的 “ 妥 协 性 产 物 ” 。\n北 约 去 年 ７ 月 已 宣 布 第 一 批 东 扩 对 象 是 波 兰 、 匈 牙 利 和 捷 克 三 国 ， 第 二 批 东 扩 要 等 到 １ ９ ９ ９ 年 ， 可 能 的 对 象 是 罗 马 尼 亚 和 斯 洛 文 尼 亚 。\n而 波 罗 的 海 三 国 加 入 北 约 的 问 题 在 克 林 顿 和 叶 利 钦 的 任 内 不 大 可 能 会 提 上 日 程 。\n有 人 指 出 ： “ 等 到 波 罗 的 海 三 国 加 入 北 约 时 ， 北 约 已 经 不 是 它 们 现 在 想 要 加 入 的 那 个 样 子 了 。 ”\n美 国 与 波 罗 的 海 三 国 签 署 伙 伴 关 系 宪 章 一 事 表 明 ， 在 美 国 的 心 目 中 ， 北 约 东 扩 是 没 有 止 境 的 。\n正 如 美 国 国 务 卿 奥 尔 布 赖 特 对 俄 罗 斯 外 长 普 里 马 科 夫 所 说 的 ： “ 在 这 个 问 题 上 ， 美 俄 两 国 只 能 保 留 不 同 意 见 。 ”\n但 是 波 罗 的 海 三 国 毕 竟 是 俄 罗 斯 的 近 邻 ， 美 国 不 能 不 顾 及 俄 罗 斯 的 反 应 。\n（ 本 报 华 盛 顿 １ 月 １ ６ 日 电 ）\n", "flag": [1, 1, 1, 0, 0, 0, 0, 0, 0, 0, 0, 0, 0, 0, 0, 0, 0, 0, 0, 0, 0, 0, 0, 0, 0, 0, 0, 0, 0, 0, 0, 0, 0, 0, 0, 0, 0, 0, 0, 0, 0, 0, 0, 0, 0, 0, 0, 0, 0, 0, 0, 0, 0, 0, 0, 0, 0, 0, 0, 0, 0, 0, 0, 0, 0, 0, 0, 0, 0, 0, 0, 0, 0, 0, 0, 0, 0, 0, 0, 0, 0, 0, 0, 0, 0, 0, 0, 0, 0, 0, 0, 0, 0, 0, 0, 0, 0, 0, 0, 0, 0, 0, 0, 0, 0, 0, 0, 0, 0, 0, 0, 0, 0, 0, 0, 0, 0, 0, 0, 0, 0, 0, 0, 0, 0, 0, 0, 0, 0, 0, 0, 0, 0, 0, 0, 0, 0, 0, 0, 0, 0, 0, 0, 0, 0, 0, 0, 0, 0, 0, 0, 0, 0, 0, 0, 0, 0, 0, 0, 0, 0, 0, 0, 0, 0, 0, 0, 0, 0, 0, 0, 0, 0, 0, 0, 0, 0, 0, 0, 0, 0, 0, 0, 0, 0, 0, 0, 0, 0, 0, 0, 0, 0, 0, 0, 0, 0, 0, 0, 0]}
{"eventpn": [339, 340], "eventspan": null, "allspan": [[20, 71], [46, 70], [53, 70], [72, 96], [73, 95], [74, 86], [76, 86], [90, 93], [97, 140], [104, 139], [106, 139], [108, 139], [110, 139], [128, 139], [141, 181], [143, 180], [144, 180], [147, 180], [147, 162], [153, 162], [154, 157], [159, 162], [163, 180], [182, 237], [182, 222], [193, 222], [224, 236], [238, 269], [238, 252], [240, 252], [254, 268], [254, 259], [265, 268], [270, 305], [275, 304], [278, 304], [280, 304], [309, 314], [310, 314], [323, 334], [325, 334], [331, 334]], "id": "2134.txt", "doc": "『 伙 伴 关 系 』 的 潜 台 词\n本 报 驻 美 国 记 者 李 云 飞\n美 国 总 统 克 林 顿 与 爱 沙 尼 亚 、 拉 脱 维 亚 和 立 陶 宛 三 国 总 统 ， 今 天 在 白 宫 正 式 签 署 美 国 与 波 罗 的 海 三 国 的 伙 伴 关 系 宪 章 。\n这 是 美 国 加 强 与 波 罗 的 海 三 国 关 系 的 新 的 引 人 注 目 行 动 。\n宪 章 的 主 要 内 容 是 ， 美 国 承 诺 对 波 罗 的 海 三 国 的 独 立 、 主 权 和 领 土 完 整 给 予 道 义 上 和 政 治 上 的 支 持 。\n美 国 还 表 明 ， 波 罗 的 海 三 国 在 条 件 成 熟 时 加 入 北 约 “ 有 利 于 欧 洲 的 稳 定 和 北 约 的 战 略 目 标 ” 。\n根 据 这 个 宪 章 的 精 神 ， 将 成 立 美 国 、 爱 沙 尼 亚 、 拉 脱 维 亚 和 立 陶 宛 的 四 方 “ 伙 伴 关 系 委 员 会 ” ， 由 美 国 副 国 务 卿 塔 尔 博 特 主 持 。\n还 将 成 立 若 干 经 济 发 展 的 工 作 小 组 ， 类 似 这 些 小 组 的 防 务 小 组 已 经 成 立 。\n克 林 顿 总 统 今 天 还 宣 布 建 立 １ ５ ０ ０ 万 美 元 的 波 罗 的 海 三 国 与 美 国 伙 伴 关 系 基 金 。\n宪 章 中 最 关 键 和 敏 感 的 部 分 是 ， 美 国 将 促 进 波 罗 的 海 三 国 加 入 北 约 ， 并 支 持 它 们 在 这 方 面 所 做 的 努 力 。\n此 间 舆 论 认 为 ， 这 表 明 美 国 对 未 来 欧 洲 防 务 的 计 划 不 只 限 于 北 约 的 第 一 轮 东 扩 。\n美 国 所 担 心 的 只 是 怕 因 此 引 起 俄 罗 斯 的 反 对 。\n实 际 上 ， 俄 罗 斯 早 已 明 确 表 示 ， 北 约 不 能 东 扩 到 波 罗 的 海 三 国 。\n俄 罗 斯 总 理 切 尔 诺 梅 尔 金 去 年 ７ 月 、 总 统 叶 利 钦 去 年 下 半 年 先 后 两 次 提 出 ， 只 要 波 罗 的 海 三 国 不 加 入 北 约 ， 俄 罗 斯 愿 意 与 北 约 及 西 方 国 家 一 起 为 这 三 国 提 供 “ 联 合 安 全 保 障 ” 。\n不 仅 俄 罗 斯 ， 美 国 的 北 约 盟 国 对 波 罗 的 海 三 国 加 入 也 持 有 很 大 的 保 留 。\n它 们 坚 持 认 为 ， 波 罗 的 海 三 国 加 入 北 约 不 仅 要 等 到 它 们 本 身 条 件 成 熟 的 时 候 ， 而 且 还 要 符 合 所 有 盟 国 的 整 体 战 略 利 益 。\n一 位 北 约 官 员 说 得 更 明 确 ， 这 在 很 大 程 度 上 取 决 于 波 罗 的 海 三 国 与 俄 罗 斯 关 系 的 改 善 。\n因 此 ， 这 个 宪 章 的 签 署 整 整 谈 了 一 年 的 时 间 ， 宪 章 关 于 这 三 国 加 入 北 约 的 问 题 ， 只 是 表 明 一 种 意 向 ， 实 际 上 在 可 预 见 的 将 来 不 会 提 出 来 。\n舆 论 认 为 ， 这 是 考 虑 到 有 关 各 方 的 态 度 ， 权 衡 利 弊 后 的 “ 妥 协 性 产 物 ” 。\n北 约 去 年 ７ 月 已 宣 布 第 一 批 东 扩 对 象 是 波 兰 、 匈 牙 利 和 捷 克 三 国 ， 第 二 批 东 扩 要 等 到 １ ９ ９ ９ 年 ， 可 能 的 对 象 是 罗 马 尼 亚 和 斯 洛 文 尼 亚 。\n而 波 罗 的 海 三 国 加 入 北 约 的 问 题 在 克 林 顿 和 叶 利 钦 的 任 内 不 大 可 能 会 提 上 日 程 。\n有 人 指 出 ： “ 等 到 波 罗 的 海 三 国 加 入 北 约 时 ， 北 约 已 经 不 是 它 们 现 在 想 要 加 入 的 那 个 样 子 了 。 ”\n美 国 与 波 罗 的 海 三 国 签 署 伙 伴 关 系 宪 章 一 事 表 明 ， 在 美 国 的 心 目 中 ， 北 约 东 扩 是 没 有 止 境 的 。\n正 如 美 国 国 务 卿 奥 尔 布 赖 特 对 俄 罗 斯 外 长 普 里 马 科 夫 所 说 的 ： “ 在 这 个 问 题 上 ， 美 俄 两 国 只 能 保 留 不 同 意 见 。 ”\n但 是 波 罗 的 海 三 国 毕 竟 是 俄 罗 斯 的 近 邻 ， 美 国 不 能 不 顾 及 俄 罗 斯 的 反 应 。\n（ 本 报 华 盛 顿 １ 月 １ ６ 日 电 ）\n", "flag": [1, 1, 1, 1, 1, 1, 1, 0, 1, 0, 1, 1, 1, 1, 1, 1, 1, 1, 1, 1, 1, 1, 1, 0, 1, 1, 1, 1, 1, 1, 0, 1, 1, 1, 1, 1, 1, 0, 1, 1, 1, 1, 0, 1, 1, 0, 0, 0, 0, 0, 1, 1, 1, 0, 0, 0, 0, 0, 0, 0, 0, 0, 0, 0, 0, 0, 0, 0, 0, 0, 0, 0, 0, 0, 0, 0, 0, 0, 0, 0, 0, 0, 0, 0, 0, 0, 0, 0, 0, 0, 0, 0, 0, 0, 0, 0, 0, 0, 0, 0, 0, 0, 0, 0, 0, 0, 0, 0, 0, 0, 0, 0, 0, 0, 0, 0, 0, 0, 0, 0, 0, 0, 0, 0, 0, 0, 0, 0, 0, 0, 0, 0, 0, 0, 0, 0, 0, 0, 0, 0, 0, 0, 0, 0, 0, 0, 0, 0, 0, 0, 0, 0, 0, 0, 0, 0, 0, 0, 0, 0, 0, 0, 0, 0, 0, 0, 0, 0, 0, 0, 0, 0, 0, 0, 0, 0, 0, 0, 0, 0, 0, 0, 0, 0, 0, 0, 0, 0, 0, 0, 0, 0, 0, 0, 0, 0, 0, 0, 0, 0]}
{"eventpn": [358, 358], "eventspan": [320, 349], "allspan": [[20, 71], [46, 70], [53, 70], [72, 96], [73, 95], [74, 86], [76, 86], [90, 93], [97, 140], [104, 139], [106, 139], [108, 139], [110, 139], [128, 139], [141, 181], [143, 180], [144, 180], [147, 180], [147, 162], [153, 162], [154, 157], [159, 162], [163, 180], [182, 237], [182, 222], [193, 222], [224, 236], [238, 269], [238, 252], [240, 252], [254, 268], [254, 259], [265, 268], [270, 305], [275, 304], [278, 304], [280, 304], [306, 350], [309, 314], [310, 314], [318, 349], [320, 349], [322, 349], [323, 349], [323, 334], [325, 334], [331, 334], [337, 349], [339, 346], [341, 346]], "id": "2134.txt", "doc": "『 伙 伴 关 系 』 的 潜 台 词\n本 报 驻 美 国 记 者 李 云 飞\n美 国 总 统 克 林 顿 与 爱 沙 尼 亚 、 拉 脱 维 亚 和 立 陶 宛 三 国 总 统 ， 今 天 在 白 宫 正 式 签 署 美 国 与 波 罗 的 海 三 国 的 伙 伴 关 系 宪 章 。\n这 是 美 国 加 强 与 波 罗 的 海 三 国 关 系 的 新 的 引 人 注 目 行 动 。\n宪 章 的 主 要 内 容 是 ， 美 国 承 诺 对 波 罗 的 海 三 国 的 独 立 、 主 权 和 领 土 完 整 给 予 道 义 上 和 政 治 上 的 支 持 。\n美 国 还 表 明 ， 波 罗 的 海 三 国 在 条 件 成 熟 时 加 入 北 约 “ 有 利 于 欧 洲 的 稳 定 和 北 约 的 战 略 目 标 ” 。\n根 据 这 个 宪 章 的 精 神 ， 将 成 立 美 国 、 爱 沙 尼 亚 、 拉 脱 维 亚 和 立 陶 宛 的 四 方 “ 伙 伴 关 系 委 员 会 ” ， 由 美 国 副 国 务 卿 塔 尔 博 特 主 持 。\n还 将 成 立 若 干 经 济 发 展 的 工 作 小 组 ， 类 似 这 些 小 组 的 防 务 小 组 已 经 成 立 。\n克 林 顿 总 统 今 天 还 宣 布 建 立 １ ５ ０ ０ 万 美 元 的 波 罗 的 海 三 国 与 美 国 伙 伴 关 系 基 金 。\n宪 章 中 最 关 键 和 敏 感 的 部 分 是 ， 美 国 将 促 进 波 罗 的 海 三 国 加 入 北 约 ， 并 支 持 它 们 在 这 方 面 所 做 的 努 力 。\n此 间 舆 论 认 为 ， 这 表 明 美 国 对 未 来 欧 洲 防 务 的 计 划 不 只 限 于 北 约 的 第 一 轮 东 扩 。\n美 国 所 担 心 的 只 是 怕 因 此 引 起 俄 罗 斯 的 反 对 。\n实 际 上 ， 俄 罗 斯 早 已 明 确 表 示 ， 北 约 不 能 东 扩 到 波 罗 的 海 三 国 。\n俄 罗 斯 总 理 切 尔 诺 梅 尔 金 去 年 ７ 月 、 总 统 叶 利 钦 去 年 下 半 年 先 后 两 次 提 出 ， 只 要 波 罗 的 海 三 国 不 加 入 北 约 ， 俄 罗 斯 愿 意 与 北 约 及 西 方 国 家 一 起 为 这 三 国 提 供 “ 联 合 安 全 保 障 ” 。\n不 仅 俄 罗 斯 ， 美 国 的 北 约 盟 国 对 波 罗 的 海 三 国 加 入 也 持 有 很 大 的 保 留 。\n它 们 坚 持 认 为 ， 波 罗 的 海 三 国 加 入 北 约 不 仅 要 等 到 它 们 本 身 条 件 成 熟 的 时 候 ， 而 且 还 要 符 合 所 有 盟 国 的 整 体 战 略 利 益 。\n一 位 北 约 官 员 说 得 更 明 确 ， 这 在 很 大 程 度 上 取 决 于 波 罗 的 海 三 国 与 俄 罗 斯 关 系 的 改 善 。\n因 此 ， 这 个 宪 章 的 签 署 整 整 谈 了 一 年 的 时 间 ， 宪 章 关 于 这 三 国 加 入 北 约 的 问 题 ， 只 是 表 明 一 种 意 向 ， 实 际 上 在 可 预 见 的 将 来 不 会 提 出 来 。\n舆 论 认 为 ， 这 是 考 虑 到 有 关 各 方 的 态 度 ， 权 衡 利 弊 后 的 “ 妥 协 性 产 物 ” 。\n北 约 去 年 ７ 月 已 宣 布 第 一 批 东 扩 对 象 是 波 兰 、 匈 牙 利 和 捷 克 三 国 ， 第 二 批 东 扩 要 等 到 １ ９ ９ ９ 年 ， 可 能 的 对 象 是 罗 马 尼 亚 和 斯 洛 文 尼 亚 。\n而 波 罗 的 海 三 国 加 入 北 约 的 问 题 在 克 林 顿 和 叶 利 钦 的 任 内 不 大 可 能 会 提 上 日 程 。\n有 人 指 出 ： “ 等 到 波 罗 的 海 三 国 加 入 北 约 时 ， 北 约 已 经 不 是 它 们 现 在 想 要 加 入 的 那 个 样 子 了 。 ”\n美 国 与 波 罗 的 海 三 国 签 署 伙 伴 关 系 宪 章 一 事 表 明 ， 在 美 国 的 心 目 中 ， 北 约 东 扩 是 没 有 止 境 的 。\n正 如 美 国 国 务 卿 奥 尔 布 赖 特 对 俄 罗 斯 外 长 普 里 马 科 夫 所 说 的 ： “ 在 这 个 问 题 上 ， 美 俄 两 国 只 能 保 留 不 同 意 见 。 ”\n但 是 波 罗 的 海 三 国 毕 竟 是 俄 罗 斯 的 近 邻 ， 美 国 不 能 不 顾 及 俄 罗 斯 的 反 应 。\n（ 本 报 华 盛 顿 １ 月 １ ６ 日 电 ）\n", "flag": [1, 1, 1, 1, 1, 1, 1, 0, 1, 0, 1, 1, 1, 1, 1, 1, 1, 1, 1, 1, 1, 1, 1, 0, 1, 1, 1, 1, 1, 1, 0, 1, 1, 1, 1, 1, 1, 0, 1, 1, 1, 1, 1, 1, 1, 0, 1, 1, 1, 1, 1, 1, 1, 1, 1, 1, 0, 0, 0, 0, 0, 0, 0, 0, 0, 0, 0, 0, 0, 0, 0, 0, 0, 0, 0, 0, 0, 0, 0, 0, 0, 0, 0, 0, 0, 0, 0, 0, 0, 0, 0, 0, 0, 0, 0, 0, 0, 0, 0, 0, 0, 0, 0, 0, 0, 0, 0, 0, 0, 0, 0, 0, 0, 0, 0, 0, 0, 0, 0, 0, 0, 0, 0, 0, 0, 0, 0, 0, 0, 0, 0, 0, 0, 0, 0, 0, 0, 0, 0, 0, 0, 0, 0, 0, 0, 0, 0, 0, 0, 0, 0, 0, 0, 0, 0, 0, 0, 0, 0, 0, 0, 0, 0, 0, 0, 0, 0, 0, 0, 0, 0, 0, 0, 0, 0, 0, 0, 0, 0, 0, 0, 0, 0, 0, 0, 0, 0, 0, 0, 0, 0, 0, 0, 0, 0, 0, 0, 0, 0, 0]}
{"eventpn": [542, 543], "eventspan": null, "allspan": [[20, 71], [46, 70], [53, 70], [72, 96], [73, 95], [74, 86], [76, 86], [90, 93], [97, 140], [104, 139], [106, 139], [108, 139], [110, 139], [128, 139], [141, 181], [143, 180], [144, 180], [147, 180], [147, 162], [153, 162], [154, 157], [159, 162], [163, 180], [182, 237], [182, 222], [193, 222], [224, 236], [238, 269], [238, 252], [240, 252], [254, 268], [254, 259], [265, 268], [270, 305], [275, 304], [278, 304], [280, 304], [306, 350], [309, 314], [310, 314], [318, 349], [320, 349], [322, 349], [323, 349], [323, 334], [325, 334], [331, 334], [337, 349], [339, 346], [341, 346], [351, 385], [355, 384], [358, 384], [359, 384], [361, 384], [373, 384], [375, 384], [386, 405], [386, 390], [392, 404], [393, 404], [394, 404], [395, 404], [397, 404], [406, 433], [413, 432], [417, 432], [420, 432], [422, 432], [423, 432], [424, 432], [425, 432], [426, 432], [434, 510], [445, 509], [455, 509], [464, 509], [467, 509], [469, 479], [475, 479], [476, 479], [484, 509], [486, 509], [500, 509], [511, 541], [524, 540], [534, 540]], "id": "2134.txt", "doc": "『 伙 伴 关 系 』 的 潜 台 词\n本 报 驻 美 国 记 者 李 云 飞\n美 国 总 统 克 林 顿 与 爱 沙 尼 亚 、 拉 脱 维 亚 和 立 陶 宛 三 国 总 统 ， 今 天 在 白 宫 正 式 签 署 美 国 与 波 罗 的 海 三 国 的 伙 伴 关 系 宪 章 。\n这 是 美 国 加 强 与 波 罗 的 海 三 国 关 系 的 新 的 引 人 注 目 行 动 。\n宪 章 的 主 要 内 容 是 ， 美 国 承 诺 对 波 罗 的 海 三 国 的 独 立 、 主 权 和 领 土 完 整 给 予 道 义 上 和 政 治 上 的 支 持 。\n美 国 还 表 明 ， 波 罗 的 海 三 国 在 条 件 成 熟 时 加 入 北 约 “ 有 利 于 欧 洲 的 稳 定 和 北 约 的 战 略 目 标 ” 。\n根 据 这 个 宪 章 的 精 神 ， 将 成 立 美 国 、 爱 沙 尼 亚 、 拉 脱 维 亚 和 立 陶 宛 的 四 方 “ 伙 伴 关 系 委 员 会 ” ， 由 美 国 副 国 务 卿 塔 尔 博 特 主 持 。\n还 将 成 立 若 干 经 济 发 展 的 工 作 小 组 ， 类 似 这 些 小 组 的 防 务 小 组 已 经 成 立 。\n克 林 顿 总 统 今 天 还 宣 布 建 立 １ ５ ０ ０ 万 美 元 的 波 罗 的 海 三 国 与 美 国 伙 伴 关 系 基 金 。\n宪 章 中 最 关 键 和 敏 感 的 部 分 是 ， 美 国 将 促 进 波 罗 的 海 三 国 加 入 北 约 ， 并 支 持 它 们 在 这 方 面 所 做 的 努 力 。\n此 间 舆 论 认 为 ， 这 表 明 美 国 对 未 来 欧 洲 防 务 的 计 划 不 只 限 于 北 约 的 第 一 轮 东 扩 。\n美 国 所 担 心 的 只 是 怕 因 此 引 起 俄 罗 斯 的 反 对 。\n实 际 上 ， 俄 罗 斯 早 已 明 确 表 示 ， 北 约 不 能 东 扩 到 波 罗 的 海 三 国 。\n俄 罗 斯 总 理 切 尔 诺 梅 尔 金 去 年 ７ 月 、 总 统 叶 利 钦 去 年 下 半 年 先 后 两 次 提 出 ， 只 要 波 罗 的 海 三 国 不 加 入 北 约 ， 俄 罗 斯 愿 意 与 北 约 及 西 方 国 家 一 起 为 这 三 国 提 供 “ 联 合 安 全 保 障 ” 。\n不 仅 俄 罗 斯 ， 美 国 的 北 约 盟 国 对 波 罗 的 海 三 国 加 入 也 持 有 很 大 的 保 留 。\n它 们 坚 持 认 为 ， 波 罗 的 海 三 国 加 入 北 约 不 仅 要 等 到 它 们 本 身 条 件 成 熟 的 时 候 ， 而 且 还 要 符 合 所 有 盟 国 的 整 体 战 略 利 益 。\n一 位 北 约 官 员 说 得 更 明 确 ， 这 在 很 大 程 度 上 取 决 于 波 罗 的 海 三 国 与 俄 罗 斯 关 系 的 改 善 。\n因 此 ， 这 个 宪 章 的 签 署 整 整 谈 了 一 年 的 时 间 ， 宪 章 关 于 这 三 国 加 入 北 约 的 问 题 ， 只 是 表 明 一 种 意 向 ， 实 际 上 在 可 预 见 的 将 来 不 会 提 出 来 。\n舆 论 认 为 ， 这 是 考 虑 到 有 关 各 方 的 态 度 ， 权 衡 利 弊 后 的 “ 妥 协 性 产 物 ” 。\n北 约 去 年 ７ 月 已 宣 布 第 一 批 东 扩 对 象 是 波 兰 、 匈 牙 利 和 捷 克 三 国 ， 第 二 批 东 扩 要 等 到 １ ９ ９ ９ 年 ， 可 能 的 对 象 是 罗 马 尼 亚 和 斯 洛 文 尼 亚 。\n而 波 罗 的 海 三 国 加 入 北 约 的 问 题 在 克 林 顿 和 叶 利 钦 的 任 内 不 大 可 能 会 提 上 日 程 。\n有 人 指 出 ： “ 等 到 波 罗 的 海 三 国 加 入 北 约 时 ， 北 约 已 经 不 是 它 们 现 在 想 要 加 入 的 那 个 样 子 了 。 ”\n美 国 与 波 罗 的 海 三 国 签 署 伙 伴 关 系 宪 章 一 事 表 明 ， 在 美 国 的 心 目 中 ， 北 约 东 扩 是 没 有 止 境 的 。\n正 如 美 国 国 务 卿 奥 尔 布 赖 特 对 俄 罗 斯 外 长 普 里 马 科 夫 所 说 的 ： “ 在 这 个 问 题 上 ， 美 俄 两 国 只 能 保 留 不 同 意 见 。 ”\n但 是 波 罗 的 海 三 国 毕 竟 是 俄 罗 斯 的 近 邻 ， 美 国 不 能 不 顾 及 俄 罗 斯 的 反 应 。\n（ 本 报 华 盛 顿 １ 月 １ ６ 日 电 ）\n", "flag": [1, 1, 1, 1, 1, 1, 1, 0, 1, 0, 1, 1, 1, 1, 1, 1, 1, 1, 1, 1, 1, 1, 1, 0, 1, 1, 1, 1, 1, 1, 0, 1, 1, 1, 1, 1, 1, 0, 1, 1, 1, 1, 1, 1, 1, 0, 1, 1, 1, 1, 1, 1, 1, 1, 1, 1, 0, 0, 1, 1, 1, 1, 1, 1, 1, 1, 1, 0, 0, 1, 1, 1, 1, 1, 1, 1, 1, 1, 1, 1, 1, 1, 1, 1, 1, 1, 1, 1, 1, 1, 1, 1, 1, 1, 1, 1, 1, 0, 0, 0, 0, 0, 0, 0, 0, 0, 0, 0, 0, 0, 0, 0, 0, 0, 0, 0, 0, 0, 0, 0, 0, 0, 0, 0, 0, 0, 0, 0, 0, 0, 0, 0, 0, 0, 0, 0, 0, 0, 0, 0, 0, 0, 0, 0, 0, 0, 0, 0, 0, 0, 0, 0, 0, 0, 0, 0, 0, 0, 0, 0, 0, 0, 0, 0, 0, 0, 0, 0, 0, 0, 0, 0, 0, 0, 0, 0, 0, 0, 0, 0, 0, 0, 0, 0, 0, 0, 0, 0, 0, 0, 0, 0, 0, 0, 0, 0, 0, 0, 0, 0]}
{"eventpn": [564, 565], "eventspan": null, "allspan": [[20, 71], [46, 70], [53, 70], [72, 96], [73, 95], [74, 86], [76, 86], [90, 93], [97, 140], [104, 139], [106, 139], [108, 139], [110, 139], [128, 139], [141, 181], [143, 180], [144, 180], [147, 180], [147, 162], [153, 162], [154, 157], [159, 162], [163, 180], [182, 237], [182, 222], [193, 222], [224, 236], [238, 269], [238, 252], [240, 252], [254, 268], [254, 259], [265, 268], [270, 305], [275, 304], [278, 304], [280, 304], [306, 350], [309, 314], [310, 314], [318, 349], [320, 349], [322, 349], [323, 349], [323, 334], [325, 334], [331, 334], [337, 349], [339, 346], [341, 346], [351, 385], [355, 384], [358, 384], [359, 384], [361, 384], [373, 384], [375, 384], [386, 405], [386, 390], [392, 404], [393, 404], [394, 404], [395, 404], [397, 404], [406, 433], [413, 432], [417, 432], [420, 432], [422, 432], [423, 432], [424, 432], [425, 432], [426, 432], [434, 510], [445, 509], [455, 509], [464, 509], [467, 509], [469, 479], [475, 479], [476, 479], [484, 509], [486, 509], [500, 509], [511, 541], [524, 540], [534, 540], [549, 558], [555, 558]], "id": "2134.txt", "doc": "『 伙 伴 关 系 』 的 潜 台 词\n本 报 驻 美 国 记 者 李 云 飞\n美 国 总 统 克 林 顿 与 爱 沙 尼 亚 、 拉 脱 维 亚 和 立 陶 宛 三 国 总 统 ， 今 天 在 白 宫 正 式 签 署 美 国 与 波 罗 的 海 三 国 的 伙 伴 关 系 宪 章 。\n这 是 美 国 加 强 与 波 罗 的 海 三 国 关 系 的 新 的 引 人 注 目 行 动 。\n宪 章 的 主 要 内 容 是 ， 美 国 承 诺 对 波 罗 的 海 三 国 的 独 立 、 主 权 和 领 土 完 整 给 予 道 义 上 和 政 治 上 的 支 持 。\n美 国 还 表 明 ， 波 罗 的 海 三 国 在 条 件 成 熟 时 加 入 北 约 “ 有 利 于 欧 洲 的 稳 定 和 北 约 的 战 略 目 标 ” 。\n根 据 这 个 宪 章 的 精 神 ， 将 成 立 美 国 、 爱 沙 尼 亚 、 拉 脱 维 亚 和 立 陶 宛 的 四 方 “ 伙 伴 关 系 委 员 会 ” ， 由 美 国 副 国 务 卿 塔 尔 博 特 主 持 。\n还 将 成 立 若 干 经 济 发 展 的 工 作 小 组 ， 类 似 这 些 小 组 的 防 务 小 组 已 经 成 立 。\n克 林 顿 总 统 今 天 还 宣 布 建 立 １ ５ ０ ０ 万 美 元 的 波 罗 的 海 三 国 与 美 国 伙 伴 关 系 基 金 。\n宪 章 中 最 关 键 和 敏 感 的 部 分 是 ， 美 国 将 促 进 波 罗 的 海 三 国 加 入 北 约 ， 并 支 持 它 们 在 这 方 面 所 做 的 努 力 。\n此 间 舆 论 认 为 ， 这 表 明 美 国 对 未 来 欧 洲 防 务 的 计 划 不 只 限 于 北 约 的 第 一 轮 东 扩 。\n美 国 所 担 心 的 只 是 怕 因 此 引 起 俄 罗 斯 的 反 对 。\n实 际 上 ， 俄 罗 斯 早 已 明 确 表 示 ， 北 约 不 能 东 扩 到 波 罗 的 海 三 国 。\n俄 罗 斯 总 理 切 尔 诺 梅 尔 金 去 年 ７ 月 、 总 统 叶 利 钦 去 年 下 半 年 先 后 两 次 提 出 ， 只 要 波 罗 的 海 三 国 不 加 入 北 约 ， 俄 罗 斯 愿 意 与 北 约 及 西 方 国 家 一 起 为 这 三 国 提 供 “ 联 合 安 全 保 障 ” 。\n不 仅 俄 罗 斯 ， 美 国 的 北 约 盟 国 对 波 罗 的 海 三 国 加 入 也 持 有 很 大 的 保 留 。\n它 们 坚 持 认 为 ， 波 罗 的 海 三 国 加 入 北 约 不 仅 要 等 到 它 们 本 身 条 件 成 熟 的 时 候 ， 而 且 还 要 符 合 所 有 盟 国 的 整 体 战 略 利 益 。\n一 位 北 约 官 员 说 得 更 明 确 ， 这 在 很 大 程 度 上 取 决 于 波 罗 的 海 三 国 与 俄 罗 斯 关 系 的 改 善 。\n因 此 ， 这 个 宪 章 的 签 署 整 整 谈 了 一 年 的 时 间 ， 宪 章 关 于 这 三 国 加 入 北 约 的 问 题 ， 只 是 表 明 一 种 意 向 ， 实 际 上 在 可 预 见 的 将 来 不 会 提 出 来 。\n舆 论 认 为 ， 这 是 考 虑 到 有 关 各 方 的 态 度 ， 权 衡 利 弊 后 的 “ 妥 协 性 产 物 ” 。\n北 约 去 年 ７ 月 已 宣 布 第 一 批 东 扩 对 象 是 波 兰 、 匈 牙 利 和 捷 克 三 国 ， 第 二 批 东 扩 要 等 到 １ ９ ９ ９ 年 ， 可 能 的 对 象 是 罗 马 尼 亚 和 斯 洛 文 尼 亚 。\n而 波 罗 的 海 三 国 加 入 北 约 的 问 题 在 克 林 顿 和 叶 利 钦 的 任 内 不 大 可 能 会 提 上 日 程 。\n有 人 指 出 ： “ 等 到 波 罗 的 海 三 国 加 入 北 约 时 ， 北 约 已 经 不 是 它 们 现 在 想 要 加 入 的 那 个 样 子 了 。 ”\n美 国 与 波 罗 的 海 三 国 签 署 伙 伴 关 系 宪 章 一 事 表 明 ， 在 美 国 的 心 目 中 ， 北 约 东 扩 是 没 有 止 境 的 。\n正 如 美 国 国 务 卿 奥 尔 布 赖 特 对 俄 罗 斯 外 长 普 里 马 科 夫 所 说 的 ： “ 在 这 个 问 题 上 ， 美 俄 两 国 只 能 保 留 不 同 意 见 。 ”\n但 是 波 罗 的 海 三 国 毕 竟 是 俄 罗 斯 的 近 邻 ， 美 国 不 能 不 顾 及 俄 罗 斯 的 反 应 。\n（ 本 报 华 盛 顿 １ 月 １ ６ 日 电 ）\n", "flag": [1, 1, 1, 1, 1, 1, 1, 0, 1, 0, 1, 1, 1, 1, 1, 1, 1, 1, 1, 1, 1, 1, 1, 0, 1, 1, 1, 1, 1, 1, 0, 1, 1, 1, 1, 1, 1, 0, 1, 1, 1, 1, 1, 1, 1, 0, 1, 1, 1, 1, 1, 1, 1, 1, 1, 1, 0, 0, 1, 1, 1, 1, 1, 1, 1, 1, 1, 0, 0, 1, 1, 1, 1, 1, 1, 1, 1, 1, 1, 1, 1, 1, 1, 1, 1, 1, 1, 1, 1, 1, 1, 1, 1, 1, 1, 1, 1, 0, 0, 0, 0, 0, 1, 1, 0, 0, 0, 0, 0, 0, 0, 0, 0, 0, 0, 0, 0, 0, 0, 0, 0, 0, 0, 0, 0, 0, 0, 0, 0, 0, 0, 0, 0, 0, 0, 0, 0, 0, 0, 0, 0, 0, 0, 0, 0, 0, 0, 0, 0, 0, 0, 0, 0, 0, 0, 0, 0, 0, 0, 0, 0, 0, 0, 0, 0, 0, 0, 0, 0, 0, 0, 0, 0, 0, 0, 0, 0, 0, 0, 0, 0, 0, 0, 0, 0, 0, 0, 0, 0, 0, 0, 0, 0, 0, 0, 0, 0, 0, 0, 0]}
{"eventpn": [566, 567], "eventspan": null, "allspan": [[20, 71], [46, 70], [53, 70], [72, 96], [73, 95], [74, 86], [76, 86], [90, 93], [97, 140], [104, 139], [106, 139], [108, 139], [110, 139], [128, 139], [141, 181], [143, 180], [144, 180], [147, 180], [147, 162], [153, 162], [154, 157], [159, 162], [163, 180], [182, 237], [182, 222], [193, 222], [224, 236], [238, 269], [238, 252], [240, 252], [254, 268], [254, 259], [265, 268], [270, 305], [275, 304], [278, 304], [280, 304], [306, 350], [309, 314], [310, 314], [318, 349], [320, 349], [322, 349], [323, 349], [323, 334], [325, 334], [331, 334], [337, 349], [339, 346], [341, 346], [351, 385], [355, 384], [358, 384], [359, 384], [361, 384], [373, 384], [375, 384], [386, 405], [386, 390], [392, 404], [393, 404], [394, 404], [395, 404], [397, 404], [406, 433], [413, 432], [417, 432], [420, 432], [422, 432], [423, 432], [424, 432], [425, 432], [426, 432], [434, 510], [445, 509], [455, 509], [464, 509], [467, 509], [469, 479], [475, 479], [476, 479], [484, 509], [486, 509], [500, 509], [511, 541], [524, 540], [534, 540], [549, 558], [555, 558]], "id": "2134.txt", "doc": "『 伙 伴 关 系 』 的 潜 台 词\n本 报 驻 美 国 记 者 李 云 飞\n美 国 总 统 克 林 顿 与 爱 沙 尼 亚 、 拉 脱 维 亚 和 立 陶 宛 三 国 总 统 ， 今 天 在 白 宫 正 式 签 署 美 国 与 波 罗 的 海 三 国 的 伙 伴 关 系 宪 章 。\n这 是 美 国 加 强 与 波 罗 的 海 三 国 关 系 的 新 的 引 人 注 目 行 动 。\n宪 章 的 主 要 内 容 是 ， 美 国 承 诺 对 波 罗 的 海 三 国 的 独 立 、 主 权 和 领 土 完 整 给 予 道 义 上 和 政 治 上 的 支 持 。\n美 国 还 表 明 ， 波 罗 的 海 三 国 在 条 件 成 熟 时 加 入 北 约 “ 有 利 于 欧 洲 的 稳 定 和 北 约 的 战 略 目 标 ” 。\n根 据 这 个 宪 章 的 精 神 ， 将 成 立 美 国 、 爱 沙 尼 亚 、 拉 脱 维 亚 和 立 陶 宛 的 四 方 “ 伙 伴 关 系 委 员 会 ” ， 由 美 国 副 国 务 卿 塔 尔 博 特 主 持 。\n还 将 成 立 若 干 经 济 发 展 的 工 作 小 组 ， 类 似 这 些 小 组 的 防 务 小 组 已 经 成 立 。\n克 林 顿 总 统 今 天 还 宣 布 建 立 １ ５ ０ ０ 万 美 元 的 波 罗 的 海 三 国 与 美 国 伙 伴 关 系 基 金 。\n宪 章 中 最 关 键 和 敏 感 的 部 分 是 ， 美 国 将 促 进 波 罗 的 海 三 国 加 入 北 约 ， 并 支 持 它 们 在 这 方 面 所 做 的 努 力 。\n此 间 舆 论 认 为 ， 这 表 明 美 国 对 未 来 欧 洲 防 务 的 计 划 不 只 限 于 北 约 的 第 一 轮 东 扩 。\n美 国 所 担 心 的 只 是 怕 因 此 引 起 俄 罗 斯 的 反 对 。\n实 际 上 ， 俄 罗 斯 早 已 明 确 表 示 ， 北 约 不 能 东 扩 到 波 罗 的 海 三 国 。\n俄 罗 斯 总 理 切 尔 诺 梅 尔 金 去 年 ７ 月 、 总 统 叶 利 钦 去 年 下 半 年 先 后 两 次 提 出 ， 只 要 波 罗 的 海 三 国 不 加 入 北 约 ， 俄 罗 斯 愿 意 与 北 约 及 西 方 国 家 一 起 为 这 三 国 提 供 “ 联 合 安 全 保 障 ” 。\n不 仅 俄 罗 斯 ， 美 国 的 北 约 盟 国 对 波 罗 的 海 三 国 加 入 也 持 有 很 大 的 保 留 。\n它 们 坚 持 认 为 ， 波 罗 的 海 三 国 加 入 北 约 不 仅 要 等 到 它 们 本 身 条 件 成 熟 的 时 候 ， 而 且 还 要 符 合 所 有 盟 国 的 整 体 战 略 利 益 。\n一 位 北 约 官 员 说 得 更 明 确 ， 这 在 很 大 程 度 上 取 决 于 波 罗 的 海 三 国 与 俄 罗 斯 关 系 的 改 善 。\n因 此 ， 这 个 宪 章 的 签 署 整 整 谈 了 一 年 的 时 间 ， 宪 章 关 于 这 三 国 加 入 北 约 的 问 题 ， 只 是 表 明 一 种 意 向 ， 实 际 上 在 可 预 见 的 将 来 不 会 提 出 来 。\n舆 论 认 为 ， 这 是 考 虑 到 有 关 各 方 的 态 度 ， 权 衡 利 弊 后 的 “ 妥 协 性 产 物 ” 。\n北 约 去 年 ７ 月 已 宣 布 第 一 批 东 扩 对 象 是 波 兰 、 匈 牙 利 和 捷 克 三 国 ， 第 二 批 东 扩 要 等 到 １ ９ ９ ９ 年 ， 可 能 的 对 象 是 罗 马 尼 亚 和 斯 洛 文 尼 亚 。\n而 波 罗 的 海 三 国 加 入 北 约 的 问 题 在 克 林 顿 和 叶 利 钦 的 任 内 不 大 可 能 会 提 上 日 程 。\n有 人 指 出 ： “ 等 到 波 罗 的 海 三 国 加 入 北 约 时 ， 北 约 已 经 不 是 它 们 现 在 想 要 加 入 的 那 个 样 子 了 。 ”\n美 国 与 波 罗 的 海 三 国 签 署 伙 伴 关 系 宪 章 一 事 表 明 ， 在 美 国 的 心 目 中 ， 北 约 东 扩 是 没 有 止 境 的 。\n正 如 美 国 国 务 卿 奥 尔 布 赖 特 对 俄 罗 斯 外 长 普 里 马 科 夫 所 说 的 ： “ 在 这 个 问 题 上 ， 美 俄 两 国 只 能 保 留 不 同 意 见 。 ”\n但 是 波 罗 的 海 三 国 毕 竟 是 俄 罗 斯 的 近 邻 ， 美 国 不 能 不 顾 及 俄 罗 斯 的 反 应 。\n（ 本 报 华 盛 顿 １ 月 １ ６ 日 电 ）\n", "flag": [1, 1, 1, 1, 1, 1, 1, 0, 1, 0, 1, 1, 1, 1, 1, 1, 1, 1, 1, 1, 1, 1, 1, 0, 1, 1, 1, 1, 1, 1, 0, 1, 1, 1, 1, 1, 1, 0, 1, 1, 1, 1, 1, 1, 1, 0, 1, 1, 1, 1, 1, 1, 1, 1, 1, 1, 0, 0, 1, 1, 1, 1, 1, 1, 1, 1, 1, 0, 0, 1, 1, 1, 1, 1, 1, 1, 1, 1, 1, 1, 1, 1, 1, 1, 1, 1, 1, 1, 1, 1, 1, 1, 1, 1, 1, 1, 1, 0, 0, 0, 0, 0, 1, 1, 0, 0, 0, 0, 0, 0, 0, 0, 0, 0, 0, 0, 0, 0, 0, 0, 0, 0, 0, 0, 0, 0, 0, 0, 0, 0, 0, 0, 0, 0, 0, 0, 0, 0, 0, 0, 0, 0, 0, 0, 0, 0, 0, 0, 0, 0, 0, 0, 0, 0, 0, 0, 0, 0, 0, 0, 0, 0, 0, 0, 0, 0, 0, 0, 0, 0, 0, 0, 0, 0, 0, 0, 0, 0, 0, 0, 0, 0, 0, 0, 0, 0, 0, 0, 0, 0, 0, 0, 0, 0, 0, 0, 0, 0, 0, 0]}
{"eventpn": [606, 606], "eventspan": [549, 558], "allspan": [[20, 71], [46, 70], [53, 70], [72, 96], [73, 95], [74, 86], [76, 86], [90, 93], [97, 140], [104, 139], [106, 139], [108, 139], [110, 139], [128, 139], [141, 181], [143, 180], [144, 180], [147, 180], [147, 162], [153, 162], [154, 157], [159, 162], [163, 180], [182, 237], [182, 222], [193, 222], [224, 236], [238, 269], [238, 252], [240, 252], [254, 268], [254, 259], [265, 268], [270, 305], [275, 304], [278, 304], [280, 304], [306, 350], [309, 314], [310, 314], [318, 349], [320, 349], [322, 349], [323, 349], [323, 334], [325, 334], [331, 334], [337, 349], [339, 346], [341, 346], [351, 385], [355, 384], [358, 384], [359, 384], [361, 384], [373, 384], [375, 384], [386, 405], [386, 390], [392, 404], [393, 404], [394, 404], [395, 404], [397, 404], [406, 433], [413, 432], [417, 432], [420, 432], [422, 432], [423, 432], [424, 432], [425, 432], [426, 432], [434, 510], [445, 509], [455, 509], [464, 509], [467, 509], [469, 479], [475, 479], [476, 479], [484, 509], [486, 509], [500, 509], [511, 541], [524, 540], [534, 540], [542, 593], [544, 592], [549, 592], [549, 558], [555, 558], [559, 592], [561, 574], [562, 574], [564, 571], [578, 592], [579, 592], [580, 592], [594, 604], [600, 604]], "id": "2134.txt", "doc": "『 伙 伴 关 系 』 的 潜 台 词\n本 报 驻 美 国 记 者 李 云 飞\n美 国 总 统 克 林 顿 与 爱 沙 尼 亚 、 拉 脱 维 亚 和 立 陶 宛 三 国 总 统 ， 今 天 在 白 宫 正 式 签 署 美 国 与 波 罗 的 海 三 国 的 伙 伴 关 系 宪 章 。\n这 是 美 国 加 强 与 波 罗 的 海 三 国 关 系 的 新 的 引 人 注 目 行 动 。\n宪 章 的 主 要 内 容 是 ， 美 国 承 诺 对 波 罗 的 海 三 国 的 独 立 、 主 权 和 领 土 完 整 给 予 道 义 上 和 政 治 上 的 支 持 。\n美 国 还 表 明 ， 波 罗 的 海 三 国 在 条 件 成 熟 时 加 入 北 约 “ 有 利 于 欧 洲 的 稳 定 和 北 约 的 战 略 目 标 ” 。\n根 据 这 个 宪 章 的 精 神 ， 将 成 立 美 国 、 爱 沙 尼 亚 、 拉 脱 维 亚 和 立 陶 宛 的 四 方 “ 伙 伴 关 系 委 员 会 ” ， 由 美 国 副 国 务 卿 塔 尔 博 特 主 持 。\n还 将 成 立 若 干 经 济 发 展 的 工 作 小 组 ， 类 似 这 些 小 组 的 防 务 小 组 已 经 成 立 。\n克 林 顿 总 统 今 天 还 宣 布 建 立 １ ５ ０ ０ 万 美 元 的 波 罗 的 海 三 国 与 美 国 伙 伴 关 系 基 金 。\n宪 章 中 最 关 键 和 敏 感 的 部 分 是 ， 美 国 将 促 进 波 罗 的 海 三 国 加 入 北 约 ， 并 支 持 它 们 在 这 方 面 所 做 的 努 力 。\n此 间 舆 论 认 为 ， 这 表 明 美 国 对 未 来 欧 洲 防 务 的 计 划 不 只 限 于 北 约 的 第 一 轮 东 扩 。\n美 国 所 担 心 的 只 是 怕 因 此 引 起 俄 罗 斯 的 反 对 。\n实 际 上 ， 俄 罗 斯 早 已 明 确 表 示 ， 北 约 不 能 东 扩 到 波 罗 的 海 三 国 。\n俄 罗 斯 总 理 切 尔 诺 梅 尔 金 去 年 ７ 月 、 总 统 叶 利 钦 去 年 下 半 年 先 后 两 次 提 出 ， 只 要 波 罗 的 海 三 国 不 加 入 北 约 ， 俄 罗 斯 愿 意 与 北 约 及 西 方 国 家 一 起 为 这 三 国 提 供 “ 联 合 安 全 保 障 ” 。\n不 仅 俄 罗 斯 ， 美 国 的 北 约 盟 国 对 波 罗 的 海 三 国 加 入 也 持 有 很 大 的 保 留 。\n它 们 坚 持 认 为 ， 波 罗 的 海 三 国 加 入 北 约 不 仅 要 等 到 它 们 本 身 条 件 成 熟 的 时 候 ， 而 且 还 要 符 合 所 有 盟 国 的 整 体 战 略 利 益 。\n一 位 北 约 官 员 说 得 更 明 确 ， 这 在 很 大 程 度 上 取 决 于 波 罗 的 海 三 国 与 俄 罗 斯 关 系 的 改 善 。\n因 此 ， 这 个 宪 章 的 签 署 整 整 谈 了 一 年 的 时 间 ， 宪 章 关 于 这 三 国 加 入 北 约 的 问 题 ， 只 是 表 明 一 种 意 向 ， 实 际 上 在 可 预 见 的 将 来 不 会 提 出 来 。\n舆 论 认 为 ， 这 是 考 虑 到 有 关 各 方 的 态 度 ， 权 衡 利 弊 后 的 “ 妥 协 性 产 物 ” 。\n北 约 去 年 ７ 月 已 宣 布 第 一 批 东 扩 对 象 是 波 兰 、 匈 牙 利 和 捷 克 三 国 ， 第 二 批 东 扩 要 等 到 １ ９ ９ ９ 年 ， 可 能 的 对 象 是 罗 马 尼 亚 和 斯 洛 文 尼 亚 。\n而 波 罗 的 海 三 国 加 入 北 约 的 问 题 在 克 林 顿 和 叶 利 钦 的 任 内 不 大 可 能 会 提 上 日 程 。\n有 人 指 出 ： “ 等 到 波 罗 的 海 三 国 加 入 北 约 时 ， 北 约 已 经 不 是 它 们 现 在 想 要 加 入 的 那 个 样 子 了 。 ”\n美 国 与 波 罗 的 海 三 国 签 署 伙 伴 关 系 宪 章 一 事 表 明 ， 在 美 国 的 心 目 中 ， 北 约 东 扩 是 没 有 止 境 的 。\n正 如 美 国 国 务 卿 奥 尔 布 赖 特 对 俄 罗 斯 外 长 普 里 马 科 夫 所 说 的 ： “ 在 这 个 问 题 上 ， 美 俄 两 国 只 能 保 留 不 同 意 见 。 ”\n但 是 波 罗 的 海 三 国 毕 竟 是 俄 罗 斯 的 近 邻 ， 美 国 不 能 不 顾 及 俄 罗 斯 的 反 应 。\n（ 本 报 华 盛 顿 １ 月 １ ６ 日 电 ）\n", "flag": [1, 1, 1, 1, 1, 1, 1, 0, 1, 0, 1, 1, 1, 1, 1, 1, 1, 1, 1, 1, 1, 1, 1, 0, 1, 1, 1, 1, 1, 1, 0, 1, 1, 1, 1, 1, 1, 0, 1, 1, 1, 1, 1, 1, 1, 0, 1, 1, 1, 1, 1, 1, 1, 1, 1, 1, 0, 0, 1, 1, 1, 1, 1, 1, 1, 1, 1, 0, 0, 1, 1, 1, 1, 1, 1, 1, 1, 1, 1, 1, 1, 1, 1, 1, 1, 1, 1, 1, 1, 1, 1, 1, 1, 1, 1, 1, 1, 0, 0, 1, 1, 1, 1, 1, 1, 1, 1, 1, 0, 1, 1, 1, 0, 1, 1, 0, 0, 0, 0, 0, 0, 0, 0, 0, 0, 0, 0, 0, 0, 0, 0, 0, 0, 0, 0, 0, 0, 0, 0, 0, 0, 0, 0, 0, 0, 0, 0, 0, 0, 0, 0, 0, 0, 0, 0, 0, 0, 0, 0, 0, 0, 0, 0, 0, 0, 0, 0, 0, 0, 0, 0, 0, 0, 0, 0, 0, 0, 0, 0, 0, 0, 0, 0, 0, 0, 0, 0, 0, 0, 0, 0, 0, 0, 0, 0, 0, 0, 0, 0, 0]}
{"eventpn": [697, 697], "eventspan": [632, 691], "allspan": [[20, 71], [46, 70], [53, 70], [72, 96], [73, 95], [74, 86], [76, 86], [90, 93], [97, 140], [104, 139], [106, 139], [108, 139], [110, 139], [128, 139], [141, 181], [143, 180], [144, 180], [147, 180], [147, 162], [153, 162], [154, 157], [159, 162], [163, 180], [182, 237], [182, 222], [193, 222], [224, 236], [238, 269], [238, 252], [240, 252], [254, 268], [254, 259], [265, 268], [270, 305], [275, 304], [278, 304], [280, 304], [306, 350], [309, 314], [310, 314], [318, 349], [320, 349], [322, 349], [323, 349], [323, 334], [325, 334], [331, 334], [337, 349], [339, 346], [341, 346], [351, 385], [355, 384], [358, 384], [359, 384], [361, 384], [373, 384], [375, 384], [386, 405], [386, 390], [392, 404], [393, 404], [394, 404], [395, 404], [397, 404], [406, 433], [413, 432], [417, 432], [420, 432], [422, 432], [423, 432], [424, 432], [425, 432], [426, 432], [434, 510], [445, 509], [455, 509], [464, 509], [467, 509], [469, 479], [475, 479], [476, 479], [484, 509], [486, 509], [500, 509], [511, 541], [524, 540], [534, 540], [542, 593], [544, 592], [549, 592], [549, 558], [555, 558], [559, 592], [561, 574], [562, 574], [564, 571], [578, 592], [579, 592], [580, 592], [594, 631], [594, 604], [600, 604], [606, 630], [607, 630], [613, 630], [632, 691], [632, 650], [642, 650], [644, 650], [652, 690], [654, 690], [654, 674], [656, 662], [659, 662], [669, 674], [676, 690], [687, 690]], "id": "2134.txt", "doc": "『 伙 伴 关 系 』 的 潜 台 词\n本 报 驻 美 国 记 者 李 云 飞\n美 国 总 统 克 林 顿 与 爱 沙 尼 亚 、 拉 脱 维 亚 和 立 陶 宛 三 国 总 统 ， 今 天 在 白 宫 正 式 签 署 美 国 与 波 罗 的 海 三 国 的 伙 伴 关 系 宪 章 。\n这 是 美 国 加 强 与 波 罗 的 海 三 国 关 系 的 新 的 引 人 注 目 行 动 。\n宪 章 的 主 要 内 容 是 ， 美 国 承 诺 对 波 罗 的 海 三 国 的 独 立 、 主 权 和 领 土 完 整 给 予 道 义 上 和 政 治 上 的 支 持 。\n美 国 还 表 明 ， 波 罗 的 海 三 国 在 条 件 成 熟 时 加 入 北 约 “ 有 利 于 欧 洲 的 稳 定 和 北 约 的 战 略 目 标 ” 。\n根 据 这 个 宪 章 的 精 神 ， 将 成 立 美 国 、 爱 沙 尼 亚 、 拉 脱 维 亚 和 立 陶 宛 的 四 方 “ 伙 伴 关 系 委 员 会 ” ， 由 美 国 副 国 务 卿 塔 尔 博 特 主 持 。\n还 将 成 立 若 干 经 济 发 展 的 工 作 小 组 ， 类 似 这 些 小 组 的 防 务 小 组 已 经 成 立 。\n克 林 顿 总 统 今 天 还 宣 布 建 立 １ ５ ０ ０ 万 美 元 的 波 罗 的 海 三 国 与 美 国 伙 伴 关 系 基 金 。\n宪 章 中 最 关 键 和 敏 感 的 部 分 是 ， 美 国 将 促 进 波 罗 的 海 三 国 加 入 北 约 ， 并 支 持 它 们 在 这 方 面 所 做 的 努 力 。\n此 间 舆 论 认 为 ， 这 表 明 美 国 对 未 来 欧 洲 防 务 的 计 划 不 只 限 于 北 约 的 第 一 轮 东 扩 。\n美 国 所 担 心 的 只 是 怕 因 此 引 起 俄 罗 斯 的 反 对 。\n实 际 上 ， 俄 罗 斯 早 已 明 确 表 示 ， 北 约 不 能 东 扩 到 波 罗 的 海 三 国 。\n俄 罗 斯 总 理 切 尔 诺 梅 尔 金 去 年 ７ 月 、 总 统 叶 利 钦 去 年 下 半 年 先 后 两 次 提 出 ， 只 要 波 罗 的 海 三 国 不 加 入 北 约 ， 俄 罗 斯 愿 意 与 北 约 及 西 方 国 家 一 起 为 这 三 国 提 供 “ 联 合 安 全 保 障 ” 。\n不 仅 俄 罗 斯 ， 美 国 的 北 约 盟 国 对 波 罗 的 海 三 国 加 入 也 持 有 很 大 的 保 留 。\n它 们 坚 持 认 为 ， 波 罗 的 海 三 国 加 入 北 约 不 仅 要 等 到 它 们 本 身 条 件 成 熟 的 时 候 ， 而 且 还 要 符 合 所 有 盟 国 的 整 体 战 略 利 益 。\n一 位 北 约 官 员 说 得 更 明 确 ， 这 在 很 大 程 度 上 取 决 于 波 罗 的 海 三 国 与 俄 罗 斯 关 系 的 改 善 。\n因 此 ， 这 个 宪 章 的 签 署 整 整 谈 了 一 年 的 时 间 ， 宪 章 关 于 这 三 国 加 入 北 约 的 问 题 ， 只 是 表 明 一 种 意 向 ， 实 际 上 在 可 预 见 的 将 来 不 会 提 出 来 。\n舆 论 认 为 ， 这 是 考 虑 到 有 关 各 方 的 态 度 ， 权 衡 利 弊 后 的 “ 妥 协 性 产 物 ” 。\n北 约 去 年 ７ 月 已 宣 布 第 一 批 东 扩 对 象 是 波 兰 、 匈 牙 利 和 捷 克 三 国 ， 第 二 批 东 扩 要 等 到 １ ９ ９ ９ 年 ， 可 能 的 对 象 是 罗 马 尼 亚 和 斯 洛 文 尼 亚 。\n而 波 罗 的 海 三 国 加 入 北 约 的 问 题 在 克 林 顿 和 叶 利 钦 的 任 内 不 大 可 能 会 提 上 日 程 。\n有 人 指 出 ： “ 等 到 波 罗 的 海 三 国 加 入 北 约 时 ， 北 约 已 经 不 是 它 们 现 在 想 要 加 入 的 那 个 样 子 了 。 ”\n美 国 与 波 罗 的 海 三 国 签 署 伙 伴 关 系 宪 章 一 事 表 明 ， 在 美 国 的 心 目 中 ， 北 约 东 扩 是 没 有 止 境 的 。\n正 如 美 国 国 务 卿 奥 尔 布 赖 特 对 俄 罗 斯 外 长 普 里 马 科 夫 所 说 的 ： “ 在 这 个 问 题 上 ， 美 俄 两 国 只 能 保 留 不 同 意 见 。 ”\n但 是 波 罗 的 海 三 国 毕 竟 是 俄 罗 斯 的 近 邻 ， 美 国 不 能 不 顾 及 俄 罗 斯 的 反 应 。\n（ 本 报 华 盛 顿 １ 月 １ ６ 日 电 ）\n", "flag": [1, 1, 1, 1, 1, 1, 1, 0, 1, 0, 1, 1, 1, 1, 1, 1, 1, 1, 1, 1, 1, 1, 1, 0, 1, 1, 1, 1, 1, 1, 0, 1, 1, 1, 1, 1, 1, 0, 1, 1, 1, 1, 1, 1, 1, 0, 1, 1, 1, 1, 1, 1, 1, 1, 1, 1, 0, 0, 1, 1, 1, 1, 1, 1, 1, 1, 1, 0, 0, 1, 1, 1, 1, 1, 1, 1, 1, 1, 1, 1, 1, 1, 1, 1, 1, 1, 1, 1, 1, 1, 1, 1, 1, 1, 1, 1, 1, 0, 0, 1, 1, 1, 1, 1, 1, 1, 1, 1, 0, 1, 1, 1, 1, 1, 1, 0, 0, 1, 1, 1, 1, 1, 1, 1, 1, 1, 1, 1, 1, 1, 1, 0, 0, 1, 0, 0, 0, 0, 0, 0, 0, 0, 0, 0, 0, 0, 0, 0, 0, 0, 0, 0, 0, 0, 0, 0, 0, 0, 0, 0, 0, 0, 0, 0, 0, 0, 0, 0, 0, 0, 0, 0, 0, 0, 0, 0, 0, 0, 0, 0, 0, 0, 0, 0, 0, 0, 0, 0, 0, 0, 0, 0, 0, 0, 0, 0, 0, 0, 0, 0]}
{"eventpn": [845, 846], "eventspan": null, "allspan": [[20, 71], [46, 70], [53, 70], [72, 96], [73, 95], [74, 86], [76, 86], [90, 93], [97, 140], [104, 139], [106, 139], [108, 139], [110, 139], [128, 139], [141, 181], [143, 180], [144, 180], [147, 180], [147, 162], [153, 162], [154, 157], [159, 162], [163, 180], [182, 237], [182, 222], [193, 222], [224, 236], [238, 269], [238, 252], [240, 252], [254, 268], [254, 259], [265, 268], [270, 305], [275, 304], [278, 304], [280, 304], [306, 350], [309, 314], [310, 314], [318, 349], [320, 349], [322, 349], [323, 349], [323, 334], [325, 334], [331, 334], [337, 349], [339, 346], [341, 346], [351, 385], [355, 384], [358, 384], [359, 384], [361, 384], [373, 384], [375, 384], [386, 405], [386, 390], [392, 404], [393, 404], [394, 404], [395, 404], [397, 404], [406, 433], [413, 432], [417, 432], [420, 432], [422, 432], [423, 432], [424, 432], [425, 432], [426, 432], [434, 510], [445, 509], [455, 509], [464, 509], [467, 509], [469, 479], [475, 479], [476, 479], [484, 509], [486, 509], [500, 509], [511, 541], [524, 540], [534, 540], [542, 593], [544, 592], [549, 592], [549, 558], [555, 558], [559, 592], [561, 574], [562, 574], [564, 571], [578, 592], [579, 592], [580, 592], [594, 631], [594, 604], [600, 604], [606, 630], [607, 630], [613, 630], [632, 691], [632, 650], [642, 650], [644, 650], [652, 690], [654, 690], [654, 674], [656, 662], [659, 662], [669, 674], [676, 690], [687, 690], [692, 723], [694, 722], [697, 722], [698, 722], [699, 713], [699, 708], [710, 713], [724, 783], [724, 751], [726, 751], [731, 751], [733, 751], [740, 751], [753, 765], [758, 765], [759, 765], [767, 782], [772, 782], [784, 818], [785, 794], [791, 794], [798, 817], [811, 817], [813, 817], [814, 817], [827, 836], [833, 836]], "id": "2134.txt", "doc": "『 伙 伴 关 系 』 的 潜 台 词\n本 报 驻 美 国 记 者 李 云 飞\n美 国 总 统 克 林 顿 与 爱 沙 尼 亚 、 拉 脱 维 亚 和 立 陶 宛 三 国 总 统 ， 今 天 在 白 宫 正 式 签 署 美 国 与 波 罗 的 海 三 国 的 伙 伴 关 系 宪 章 。\n这 是 美 国 加 强 与 波 罗 的 海 三 国 关 系 的 新 的 引 人 注 目 行 动 。\n宪 章 的 主 要 内 容 是 ， 美 国 承 诺 对 波 罗 的 海 三 国 的 独 立 、 主 权 和 领 土 完 整 给 予 道 义 上 和 政 治 上 的 支 持 。\n美 国 还 表 明 ， 波 罗 的 海 三 国 在 条 件 成 熟 时 加 入 北 约 “ 有 利 于 欧 洲 的 稳 定 和 北 约 的 战 略 目 标 ” 。\n根 据 这 个 宪 章 的 精 神 ， 将 成 立 美 国 、 爱 沙 尼 亚 、 拉 脱 维 亚 和 立 陶 宛 的 四 方 “ 伙 伴 关 系 委 员 会 ” ， 由 美 国 副 国 务 卿 塔 尔 博 特 主 持 。\n还 将 成 立 若 干 经 济 发 展 的 工 作 小 组 ， 类 似 这 些 小 组 的 防 务 小 组 已 经 成 立 。\n克 林 顿 总 统 今 天 还 宣 布 建 立 １ ５ ０ ０ 万 美 元 的 波 罗 的 海 三 国 与 美 国 伙 伴 关 系 基 金 。\n宪 章 中 最 关 键 和 敏 感 的 部 分 是 ， 美 国 将 促 进 波 罗 的 海 三 国 加 入 北 约 ， 并 支 持 它 们 在 这 方 面 所 做 的 努 力 。\n此 间 舆 论 认 为 ， 这 表 明 美 国 对 未 来 欧 洲 防 务 的 计 划 不 只 限 于 北 约 的 第 一 轮 东 扩 。\n美 国 所 担 心 的 只 是 怕 因 此 引 起 俄 罗 斯 的 反 对 。\n实 际 上 ， 俄 罗 斯 早 已 明 确 表 示 ， 北 约 不 能 东 扩 到 波 罗 的 海 三 国 。\n俄 罗 斯 总 理 切 尔 诺 梅 尔 金 去 年 ７ 月 、 总 统 叶 利 钦 去 年 下 半 年 先 后 两 次 提 出 ， 只 要 波 罗 的 海 三 国 不 加 入 北 约 ， 俄 罗 斯 愿 意 与 北 约 及 西 方 国 家 一 起 为 这 三 国 提 供 “ 联 合 安 全 保 障 ” 。\n不 仅 俄 罗 斯 ， 美 国 的 北 约 盟 国 对 波 罗 的 海 三 国 加 入 也 持 有 很 大 的 保 留 。\n它 们 坚 持 认 为 ， 波 罗 的 海 三 国 加 入 北 约 不 仅 要 等 到 它 们 本 身 条 件 成 熟 的 时 候 ， 而 且 还 要 符 合 所 有 盟 国 的 整 体 战 略 利 益 。\n一 位 北 约 官 员 说 得 更 明 确 ， 这 在 很 大 程 度 上 取 决 于 波 罗 的 海 三 国 与 俄 罗 斯 关 系 的 改 善 。\n因 此 ， 这 个 宪 章 的 签 署 整 整 谈 了 一 年 的 时 间 ， 宪 章 关 于 这 三 国 加 入 北 约 的 问 题 ， 只 是 表 明 一 种 意 向 ， 实 际 上 在 可 预 见 的 将 来 不 会 提 出 来 。\n舆 论 认 为 ， 这 是 考 虑 到 有 关 各 方 的 态 度 ， 权 衡 利 弊 后 的 “ 妥 协 性 产 物 ” 。\n北 约 去 年 ７ 月 已 宣 布 第 一 批 东 扩 对 象 是 波 兰 、 匈 牙 利 和 捷 克 三 国 ， 第 二 批 东 扩 要 等 到 １ ９ ９ ９ 年 ， 可 能 的 对 象 是 罗 马 尼 亚 和 斯 洛 文 尼 亚 。\n而 波 罗 的 海 三 国 加 入 北 约 的 问 题 在 克 林 顿 和 叶 利 钦 的 任 内 不 大 可 能 会 提 上 日 程 。\n有 人 指 出 ： “ 等 到 波 罗 的 海 三 国 加 入 北 约 时 ， 北 约 已 经 不 是 它 们 现 在 想 要 加 入 的 那 个 样 子 了 。 ”\n美 国 与 波 罗 的 海 三 国 签 署 伙 伴 关 系 宪 章 一 事 表 明 ， 在 美 国 的 心 目 中 ， 北 约 东 扩 是 没 有 止 境 的 。\n正 如 美 国 国 务 卿 奥 尔 布 赖 特 对 俄 罗 斯 外 长 普 里 马 科 夫 所 说 的 ： “ 在 这 个 问 题 上 ， 美 俄 两 国 只 能 保 留 不 同 意 见 。 ”\n但 是 波 罗 的 海 三 国 毕 竟 是 俄 罗 斯 的 近 邻 ， 美 国 不 能 不 顾 及 俄 罗 斯 的 反 应 。\n（ 本 报 华 盛 顿 １ 月 １ ６ 日 电 ）\n", "flag": [1, 1, 1, 1, 1, 1, 1, 0, 1, 0, 1, 1, 1, 1, 1, 1, 1, 1, 1, 1, 1, 1, 1, 0, 1, 1, 1, 1, 1, 1, 0, 1, 1, 1, 1, 1, 1, 0, 1, 1, 1, 1, 1, 1, 1, 0, 1, 1, 1, 1, 1, 1, 1, 1, 1, 1, 0, 0, 1, 1, 1, 1, 1, 1, 1, 1, 1, 0, 0, 1, 1, 1, 1, 1, 1, 1, 1, 1, 1, 1, 1, 1, 1, 1, 1, 1, 1, 1, 1, 1, 1, 1, 1, 1, 1, 1, 1, 0, 0, 1, 1, 1, 1, 1, 1, 1, 1, 1, 0, 1, 1, 1, 1, 1, 1, 0, 0, 1, 1, 1, 1, 1, 1, 1, 1, 1, 1, 1, 1, 1, 1, 0, 0, 1, 0, 1, 1, 1, 1, 1, 1, 1, 1, 1, 1, 1, 1, 1, 1, 1, 1, 1, 0, 1, 1, 1, 1, 1, 1, 1, 1, 0, 0, 0, 0, 0, 0, 1, 1, 0, 0, 0, 0, 0, 0, 0, 0, 0, 0, 0, 0, 0, 0, 0, 0, 0, 0, 0, 0, 0, 0, 0, 0, 0, 0, 0, 0, 0, 0, 0]}
