{"eventpn": [146, 146], "eventspan": [131, 144], "allspan": [[131, 144], [133, 144], [139, 144]], "id": "2304.txt", "doc": "据 居 民 们 反 映 ， 在 首 都 边 沿 区 域 ， 过 去 夜 间 常 有 暴 徒 在 黑 暗 街 口 持 枪 抢 劫 ， 晚 上 人 们 出 门 担 惊 受 怕 。\n现 在 实 行 联 防 ， 街 灯 也 亮 堂 了 ， 人 们 外 出 有 了 安 全 感 。\n一 位 名 叫 巴 拉 吉 尼 的 治 安 委 员 会 成 员 说 ： 『 把 我 们 这 些 最 了 解 街 道 情 况 的 人 组 织 起 来 ， 那 些 犯 罪 分 子 就 感 到 随 时 有 人 监 视 ， 不 敢 轻 举 妄 动 』 ， 『 我 们 用 电 话 同 警 察 保 持 密 切 联 系 ， 这 就 如 同 对 犯 罪 分 子 撒 下 了 天 罗 地 网 』 。\n鉴 于 这 些 委 员 会 成 立 后 当 地 几 个 街 区 治 安 情 况 明 显 改 善 ， 市 政 府 决 定 立 即 在 城 南 河 口 贫 民 区 推 广 这 一 做 法 ， 并 计 划 年 内 让 『 防 止 暴 力 与 犯 罪 委 员 会 』 遍 布 全 市 。\n（ 本 报 布 宜 诺 斯 艾 利 斯 一 月 十 八 日 电 ）\n", "flag": [1, 1, 1]}
