{"eventpn": [63, 64], "eventspan": null, "allspan": [[0, 28], [0, 13], [0, 10], [0, 3], [2, 3], [11, 13], [12, 13], [25, 28], [27, 28], [29, 105], [62, 66], [65, 66], [68, 104], [74, 95], [74, 88], [76, 88], [90, 95], [101, 104], [102, 104], [106, 133], [128, 132], [131, 132]], "id": "1221.txt", "doc": "肝 胆 相 照 结 同 仁 科 研 道 路 共 登 攀 吴 孟 超 肝 胆 外 科 医 学 基 金 首 次 颁 奖\n本 报 上 海 １ 月 １ １ 日 电 〓 今 天 上 午 ， 首 届 吴 孟 超 肝 胆 外 科 医 学 基 金 颁 奖 仪 式 在 这 里 举 行 ， 顾 健 人 等 ７ 名 多 年 从 事 肝 胆 外 科 基 础 和 临 床 研 究 并 取 得 显 著 成 就 的 专 家 教 授 喜 获 该 奖 。\n中 科 院 院 士 谈 家 桢 、 总 后 勤 部 卫 生 部 副 部 长 傅 征 等 向 他 们 颁 奖 。\n", "flag": [1, 1, 1, 1, 0, 0, 0, 1, 0, 0, 0, 0, 0, 0, 0, 0, 0, 0, 0, 0, 0, 0]}
