{"eventpn": [811, 811], "eventspan": [797, 809], "allspan": [[0, 6], [7, 47], [13, 46], [13, 24], [16, 24], [16, 20], [21, 24], [26, 46], [29, 46], [34, 40], [39, 40], [48, 94], [61, 68], [64, 68], [77, 93], [77, 81], [83, 93], [86, 87], [95, 121], [100, 104], [109, 120], [109, 114], [111, 114], [116, 120], [118, 120], [122, 127], [123, 125], [128, 167], [128, 154], [130, 131], [135, 154], [135, 139], [135, 136], [137, 139], [141, 154], [142, 154], [143, 154], [145, 154], [156, 166], [163, 166], [165, 166], [168, 174], [170, 173], [175, 206], [175, 195], [178, 195], [179, 195], [180, 195], [186, 195], [186, 191], [192, 195], [195, 195], [197, 205], [198, 205], [200, 205], [202, 205], [213, 225], [219, 224], [221, 224], [226, 234], [231, 234], [232, 234], [237, 240], [238, 240], [239, 240], [244, 277], [244, 260], [247, 260], [247, 249], [248, 249], [251, 260], [252, 253], [253, 253], [255, 260], [263, 268], [264, 268], [270, 274], [272, 274], [273, 274], [278, 301], [282, 299], [285, 299], [286, 292], [288, 292], [295, 299], [297, 299], [302, 334], [305, 332], [305, 309], [311, 332], [313, 332], [314, 317], [314, 315], [316, 317], [317, 317], [319, 324], [322, 324], [326, 332], [326, 329], [326, 327], [327, 327], [329, 329], [330, 332], [331, 332], [335, 360], [335, 338], [337, 338], [338, 338], [340, 359], [342, 359], [343, 359], [347, 359], [347, 350], [352, 359], [354, 359], [355, 359], [355, 356], [357, 359], [361, 372], [361, 365], [362, 365], [367, 371], [373, 397], [373, 389], [377, 389], [379, 389], [380, 389], [380, 385], [384, 385], [386, 389], [387, 389], [391, 396], [395, 396], [396, 396], [398, 434], [398, 422], [398, 406], [402, 406], [404, 406], [405, 406], [412, 422], [416, 419], [418, 419], [424, 433], [426, 433], [428, 433], [431, 433], [435, 440], [436, 438], [441, 460], [444, 459], [444, 447], [449, 459], [451, 459], [457, 459], [461, 521], [465, 519], [465, 480], [467, 480], [474, 477], [483, 519], [485, 519], [486, 491], [489, 490], [490, 490], [493, 506], [496, 506], [496, 498], [499, 506], [500, 506], [505, 506], [508, 519], [513, 519], [514, 519], [522, 545], [524, 544], [524, 537], [524, 528], [530, 537], [532, 537], [533, 537], [533, 535], [536, 537], [539, 544], [539, 540], [540, 540], [542, 544], [546, 572], [555, 571], [555, 560], [555, 558], [559, 560], [562, 571], [563, 571], [567, 571], [573, 595], [575, 594], [575, 578], [580, 594], [582, 594], [587, 594], [596, 649], [596, 605], [600, 605], [608, 612], [618, 648], [618, 622], [619, 622], [624, 627], [625, 627], [629, 640], [629, 632], [634, 640], [642, 648], [650, 681], [650, 660], [653, 660], [654, 660], [655, 660], [659, 660], [662, 680], [668, 680], [672, 680], [682, 737], [684, 709], [684, 687], [693, 709], [700, 709], [700, 703], [702, 703], [705, 709], [731, 736], [732, 736], [732, 733], [734, 736], [738, 764], [745, 763], [745, 746], [746, 746], [748, 763], [750, 763], [753, 757], [756, 757], [765, 796], [765, 768], [767, 768], [770, 795], [772, 795], [775, 795], [775, 789], [791, 795], [792, 795], [793, 795], [794, 795], [797, 818], [797, 809], [799, 809], [799, 802], [801, 802], [805, 809], [806, 809], [808, 809], [811, 816], [812, 816], [813, 816]], "id": "1580.txt", "doc": "警 惕 “ 连 环 骗 ”\n我 的 一 位 亲 友 由 北 京 乘 长 途 汽 车 来 石 家 庄 ， 在 车 上 目 睹 了 一 起 由 一 伙 骗 子 操 纵 的 “ 连 环 骗 ” 。\n去 年 １ ０ 月 ２ ０ 日 下 午 ， 一 辆 自 北 京 开 往 石 家 庄 的 长 途 国 营 大 客 车 满 载 着 乘 客 ， 奔 驰 在 坦 直 的 京 石 公 路 上 。\n忽 然 ， 一 个 坐 在 车 前 排 的 小 伙 子 大 声 叫 了 起 来 ： “ 我 中 奖 了 ！\n我 中 奖 了 ！ ”\n几 位 好 奇 的 旅 客 闻 声 凑 过 去 ， 见 他 手 中 拿 着 一 个 健 力 宝 易 拉 罐 ， 拉 环 上 中 奖 标 记 赫 然 入 目 。\n人 们 半 信 半 疑 。\n这 时 ， 又 有 一 个 中 年 男 人 拿 出 一 本 杂 志 给 大 家 看 ： “ 嗬 ， 还 真 中 了 大 奖 ！\n１ ０ 万 元 哪 ！\n这 不 ， 杂 志 上 登 得 明 明 白 白 。\n这 下 你 小 子 可 发 大 财 啦 ！\n快 去 领 奖 吧 。 ”\n小 伙 子 很 激 动 ， 但 很 快 又 显 出 为 难 神 情 ： “ 我 没 有 身 份 证 ， 怎 么 去 领 奖 呢 ？ ”\n中 年 男 人 劝 他 ： “ 要 不 转 让 给 别 人 吧 ， 可 别 作 废 了 。 ”\n小 伙 子 犹 豫 了 一 下 ， 说 ： “ 卖 了 也 行 ， 不 过 我 要 现 钱 ， 谁 出 的 多 就 给 谁 。 ”\n话 音 刚 落 ， 立 刻 有 几 个 男 人 围 了 上 去 ， 议 论 要 凑 钱 买 下 来 。\n可 凑 了 半 天 ， 只 有 几 千 元 。\n其 中 一 人 声 言 要 和 小 伙 子 下 车 去 取 存 款 ， 但 小 伙 子 不 干 。\n这 场 交 易 眼 看 要 泡 汤 时 ， 车 中 部 站 起 一 个 商 人 打 扮 的 男 人 ， 大 声 问 ： “ 外 币 卖 不 卖 ？\n我 有 英 镑 ！ ”\n小 伙 子 想 了 一 下 ， 答 应 以 ２ 万 元 价 格 卖 给 他 。\n那 位 商 人 当 即 点 给 小 伙 子 一 沓 花 花 绿 绿 的 外 币 ， 并 说 ： “ 这 下 你 可 赚 了 ， 这 英 镑 到 银 行 可 按 １ 比 １ ３ 兑 换 ， １ ０ ０ 英 镑 能 换 １ ３ ０ ０ 元 。 ”\n商 人 收 起 易 拉 罐 ， 声 称 要 去 广 东 领 奖 ， 很 快 就 下 车 了 。\n这 时 ， 那 个 中 年 男 人 找 小 伙 子 商 量 ， 要 用 人 民 币 换 他 的 外 币 。\n两 人 讨 价 还 价 ， 商 定 １ ０ ０ 英 镑 换 ８ ０ ０ 元 人 民 币 。\n中 年 男 人 换 走 几 百 英 镑 后 ， 坐 在 不 远 处 的 一 位 老 妪 见 有 利 可 图 ， 也 动 了 心 ， 颤 颤 巍 巍 地 掏 出 １ ６ ０ ０ 元 ， 换 了 ２ ０ ０ 英 镑 。\n此 后 ， 又 有 几 位 乘 客 参 与 ， 数 千 元 人 民 币 顷 刻 之 间 成 了 小 伙 子 囊 中 之 物 。\n正 当 买 到 外 币 的 几 位 乘 客 在 汽 车 的 颠 簸 中 昏 然 打 盹 ， 做 着 发 财 梦 时 ， 那 小 伙 子 、 中 年 男 人 以 及 那 几 个 “ 凑 钱 人 ” 却 下 车 溜 走 了 。\n这 场 戏 ， 明 眼 人 一 看 便 知 ， 是 一 个 用 假 币 骗 钱 的 “ 连 环 骗 ” 。\n令 人 深 思 的 是 ， 这 件 事 发 生 在 光 天 化 日 之 下 的 国 营 客 车 上 ， 却 无 人 过 问 。\n骗 术 虽 不 高 明 ， 却 能 屡 屡 得 手 ， 这 又 说 明 什 么 呢 ？\n（ 河 北 石 家 庄 市 顾 克 ）\n", "flag": [0, 0, 0, 0, 0, 0, 0, 0, 0, 0, 0, 0, 0, 0, 0, 0, 0, 0, 0, 0, 0, 0, 0, 0, 0, 0, 0, 0, 0, 0, 0, 0, 0, 0, 0, 0, 0, 0, 0, 0, 0, 0, 0, 0, 0, 0, 0, 0, 0, 0, 0, 0, 0, 0, 0, 0, 0, 0, 0, 0, 0, 0, 0, 0, 0, 0, 0, 0, 0, 0, 0, 0, 0, 0, 0, 0, 0, 0, 0, 0, 0, 0, 0, 0, 0, 0, 0, 0, 0, 0, 0, 0, 0, 0, 0, 0, 0, 0, 0, 0, 0, 0, 0, 0, 0, 0, 0, 0, 0, 0, 0, 0, 0, 0, 0, 0, 0, 0, 0, 0, 0, 0, 0, 0, 0, 0, 0, 0, 0, 0, 0, 0, 0, 0, 0, 0, 0, 0, 0, 0, 0, 0, 0, 0, 0, 0, 0, 0, 0, 0, 0, 0, 0, 0, 0, 0, 0, 0, 0, 0, 0, 0, 0, 0, 0, 0, 0, 0, 0, 0, 0, 0, 0, 0, 0, 0, 0, 0, 0, 0, 0, 0, 0, 0, 0, 0, 0, 0, 0, 0, 0, 0, 0, 0, 0, 0, 0, 0, 0, 0, 0, 0, 0, 0, 0, 0, 0, 0, 0, 0, 0, 0, 0, 0, 0, 0, 0, 0, 0, 0, 0, 0, 0, 0, 0, 0, 0, 0, 0, 0, 0, 0, 0, 0, 0, 0, 0, 0, 0, 0, 0, 0, 0, 0, 0, 0, 0, 0, 0, 0, 0, 0, 0, 0, 0, 1, 1, 1, 0, 1, 1, 0, 0, 0, 0]}
{"eventpn": [811, 811], "eventspan": [797, 809], "allspan": [[797, 809]], "id": "1580.txt", "doc": "警 惕 “ 连 环 骗 ”\n我 的 一 位 亲 友 由 北 京 乘 长 途 汽 车 来 石 家 庄 ， 在 车 上 目 睹 了 一 起 由 一 伙 骗 子 操 纵 的 “ 连 环 骗 ” 。\n去 年 １ ０ 月 ２ ０ 日 下 午 ， 一 辆 自 北 京 开 往 石 家 庄 的 长 途 国 营 大 客 车 满 载 着 乘 客 ， 奔 驰 在 坦 直 的 京 石 公 路 上 。\n忽 然 ， 一 个 坐 在 车 前 排 的 小 伙 子 大 声 叫 了 起 来 ： “ 我 中 奖 了 ！\n我 中 奖 了 ！ ”\n几 位 好 奇 的 旅 客 闻 声 凑 过 去 ， 见 他 手 中 拿 着 一 个 健 力 宝 易 拉 罐 ， 拉 环 上 中 奖 标 记 赫 然 入 目 。\n人 们 半 信 半 疑 。\n这 时 ， 又 有 一 个 中 年 男 人 拿 出 一 本 杂 志 给 大 家 看 ： “ 嗬 ， 还 真 中 了 大 奖 ！\n１ ０ 万 元 哪 ！\n这 不 ， 杂 志 上 登 得 明 明 白 白 。\n这 下 你 小 子 可 发 大 财 啦 ！\n快 去 领 奖 吧 。 ”\n小 伙 子 很 激 动 ， 但 很 快 又 显 出 为 难 神 情 ： “ 我 没 有 身 份 证 ， 怎 么 去 领 奖 呢 ？ ”\n中 年 男 人 劝 他 ： “ 要 不 转 让 给 别 人 吧 ， 可 别 作 废 了 。 ”\n小 伙 子 犹 豫 了 一 下 ， 说 ： “ 卖 了 也 行 ， 不 过 我 要 现 钱 ， 谁 出 的 多 就 给 谁 。 ”\n话 音 刚 落 ， 立 刻 有 几 个 男 人 围 了 上 去 ， 议 论 要 凑 钱 买 下 来 。\n可 凑 了 半 天 ， 只 有 几 千 元 。\n其 中 一 人 声 言 要 和 小 伙 子 下 车 去 取 存 款 ， 但 小 伙 子 不 干 。\n这 场 交 易 眼 看 要 泡 汤 时 ， 车 中 部 站 起 一 个 商 人 打 扮 的 男 人 ， 大 声 问 ： “ 外 币 卖 不 卖 ？\n我 有 英 镑 ！ ”\n小 伙 子 想 了 一 下 ， 答 应 以 ２ 万 元 价 格 卖 给 他 。\n那 位 商 人 当 即 点 给 小 伙 子 一 沓 花 花 绿 绿 的 外 币 ， 并 说 ： “ 这 下 你 可 赚 了 ， 这 英 镑 到 银 行 可 按 １ 比 １ ３ 兑 换 ， １ ０ ０ 英 镑 能 换 １ ３ ０ ０ 元 。 ”\n商 人 收 起 易 拉 罐 ， 声 称 要 去 广 东 领 奖 ， 很 快 就 下 车 了 。\n这 时 ， 那 个 中 年 男 人 找 小 伙 子 商 量 ， 要 用 人 民 币 换 他 的 外 币 。\n两 人 讨 价 还 价 ， 商 定 １ ０ ０ 英 镑 换 ８ ０ ０ 元 人 民 币 。\n中 年 男 人 换 走 几 百 英 镑 后 ， 坐 在 不 远 处 的 一 位 老 妪 见 有 利 可 图 ， 也 动 了 心 ， 颤 颤 巍 巍 地 掏 出 １ ６ ０ ０ 元 ， 换 了 ２ ０ ０ 英 镑 。\n此 后 ， 又 有 几 位 乘 客 参 与 ， 数 千 元 人 民 币 顷 刻 之 间 成 了 小 伙 子 囊 中 之 物 。\n正 当 买 到 外 币 的 几 位 乘 客 在 汽 车 的 颠 簸 中 昏 然 打 盹 ， 做 着 发 财 梦 时 ， 那 小 伙 子 、 中 年 男 人 以 及 那 几 个 “ 凑 钱 人 ” 却 下 车 溜 走 了 。\n这 场 戏 ， 明 眼 人 一 看 便 知 ， 是 一 个 用 假 币 骗 钱 的 “ 连 环 骗 ” 。\n令 人 深 思 的 是 ， 这 件 事 发 生 在 光 天 化 日 之 下 的 国 营 客 车 上 ， 却 无 人 过 问 。\n骗 术 虽 不 高 明 ， 却 能 屡 屡 得 手 ， 这 又 说 明 什 么 呢 ？\n（ 河 北 石 家 庄 市 顾 克 ）\n", "flag": [1]}
{"eventpn": [811, 811], "eventspan": [797, 809], "allspan": [[797, 809]], "id": "1580.txt", "doc": "警 惕 “ 连 环 骗 ”\n我 的 一 位 亲 友 由 北 京 乘 长 途 汽 车 来 石 家 庄 ， 在 车 上 目 睹 了 一 起 由 一 伙 骗 子 操 纵 的 “ 连 环 骗 ” 。\n去 年 １ ０ 月 ２ ０ 日 下 午 ， 一 辆 自 北 京 开 往 石 家 庄 的 长 途 国 营 大 客 车 满 载 着 乘 客 ， 奔 驰 在 坦 直 的 京 石 公 路 上 。\n忽 然 ， 一 个 坐 在 车 前 排 的 小 伙 子 大 声 叫 了 起 来 ： “ 我 中 奖 了 ！\n我 中 奖 了 ！ ”\n几 位 好 奇 的 旅 客 闻 声 凑 过 去 ， 见 他 手 中 拿 着 一 个 健 力 宝 易 拉 罐 ， 拉 环 上 中 奖 标 记 赫 然 入 目 。\n人 们 半 信 半 疑 。\n这 时 ， 又 有 一 个 中 年 男 人 拿 出 一 本 杂 志 给 大 家 看 ： “ 嗬 ， 还 真 中 了 大 奖 ！\n１ ０ 万 元 哪 ！\n这 不 ， 杂 志 上 登 得 明 明 白 白 。\n这 下 你 小 子 可 发 大 财 啦 ！\n快 去 领 奖 吧 。 ”\n小 伙 子 很 激 动 ， 但 很 快 又 显 出 为 难 神 情 ： “ 我 没 有 身 份 证 ， 怎 么 去 领 奖 呢 ？ ”\n中 年 男 人 劝 他 ： “ 要 不 转 让 给 别 人 吧 ， 可 别 作 废 了 。 ”\n小 伙 子 犹 豫 了 一 下 ， 说 ： “ 卖 了 也 行 ， 不 过 我 要 现 钱 ， 谁 出 的 多 就 给 谁 。 ”\n话 音 刚 落 ， 立 刻 有 几 个 男 人 围 了 上 去 ， 议 论 要 凑 钱 买 下 来 。\n可 凑 了 半 天 ， 只 有 几 千 元 。\n其 中 一 人 声 言 要 和 小 伙 子 下 车 去 取 存 款 ， 但 小 伙 子 不 干 。\n这 场 交 易 眼 看 要 泡 汤 时 ， 车 中 部 站 起 一 个 商 人 打 扮 的 男 人 ， 大 声 问 ： “ 外 币 卖 不 卖 ？\n我 有 英 镑 ！ ”\n小 伙 子 想 了 一 下 ， 答 应 以 ２ 万 元 价 格 卖 给 他 。\n那 位 商 人 当 即 点 给 小 伙 子 一 沓 花 花 绿 绿 的 外 币 ， 并 说 ： “ 这 下 你 可 赚 了 ， 这 英 镑 到 银 行 可 按 １ 比 １ ３ 兑 换 ， １ ０ ０ 英 镑 能 换 １ ３ ０ ０ 元 。 ”\n商 人 收 起 易 拉 罐 ， 声 称 要 去 广 东 领 奖 ， 很 快 就 下 车 了 。\n这 时 ， 那 个 中 年 男 人 找 小 伙 子 商 量 ， 要 用 人 民 币 换 他 的 外 币 。\n两 人 讨 价 还 价 ， 商 定 １ ０ ０ 英 镑 换 ８ ０ ０ 元 人 民 币 。\n中 年 男 人 换 走 几 百 英 镑 后 ， 坐 在 不 远 处 的 一 位 老 妪 见 有 利 可 图 ， 也 动 了 心 ， 颤 颤 巍 巍 地 掏 出 １ ６ ０ ０ 元 ， 换 了 ２ ０ ０ 英 镑 。\n此 后 ， 又 有 几 位 乘 客 参 与 ， 数 千 元 人 民 币 顷 刻 之 间 成 了 小 伙 子 囊 中 之 物 。\n正 当 买 到 外 币 的 几 位 乘 客 在 汽 车 的 颠 簸 中 昏 然 打 盹 ， 做 着 发 财 梦 时 ， 那 小 伙 子 、 中 年 男 人 以 及 那 几 个 “ 凑 钱 人 ” 却 下 车 溜 走 了 。\n这 场 戏 ， 明 眼 人 一 看 便 知 ， 是 一 个 用 假 币 骗 钱 的 “ 连 环 骗 ” 。\n令 人 深 思 的 是 ， 这 件 事 发 生 在 光 天 化 日 之 下 的 国 营 客 车 上 ， 却 无 人 过 问 。\n骗 术 虽 不 高 明 ， 却 能 屡 屡 得 手 ， 这 又 说 明 什 么 呢 ？\n（ 河 北 石 家 庄 市 顾 克 ）\n", "flag": [1]}
