{"eventpn": [387, 388], "eventspan": [363, 383], "allspan": [[0, 27], [22, 27], [22, 25], [26, 27], [28, 83], [71, 82], [84, 112], [96, 111], [101, 111], [113, 146], [116, 145], [117, 134], [119, 134], [120, 130], [133, 134], [140, 145], [147, 229], [147, 177], [156, 177], [156, 166], [168, 177], [173, 175], [174, 175], [179, 201], [179, 185], [189, 201], [195, 201], [204, 213], [206, 213], [208, 213], [215, 228], [218, 220], [225, 228], [227, 228], [230, 275], [232, 237], [236, 237], [260, 274], [269, 274], [276, 327], [277, 301], [278, 301], [280, 285], [291, 301], [293, 301], [296, 298], [307, 326], [308, 317], [310, 310], [320, 326], [322, 323], [328, 362], [337, 350], [337, 341], [340, 341], [344, 350], [349, 350], [358, 361], [360, 361], [363, 383], [376, 382], [381, 382], [384, 431], [384, 418], [384, 395], [385, 395], [417, 418], [420, 430], [432, 490], [438, 446], [445, 446], [459, 489], [459, 462], [461, 462], [465, 476], [468, 473], [478, 489], [481, 486], [483, 486], [491, 524], [495, 523], [498, 523], [501, 523]], "id": "733.txt", "doc": "清 华 科 研 成 果 转 化 新 机 制 挂 果 大 型 集 装 箱 检 测 系 统 『 孵 化 』 成 型\n本 报 北 京 １ 月 ７ 日 讯 〓 记 者 杨 健 报 道 ： 经 过 近 两 年 艰 苦 努 力 ， 我 国 第 一 套 国 产 大 型 集 装 箱 检 测 系 统 完 成 了 由 成 果 向 产 品 的 转 化 。\n今 天 ， 该 项 目 的 产 品 化 工 作 在 清 华 大 学 通 过 了 专 家 委 员 会 的 审 定 。\n专 家 们 对 该 校 在 探 索 科 研 成 果 转 化 新 机 制 方 面 取 得 的 这 一 成 绩 给 予 高 度 评 价 。\n大 型 集 装 箱 检 测 系 统 利 用 核 辐 射 扫 描 成 像 技 术 ， 实 现 集 装 箱 免 开 箱 检 测 ， 扫 描 一 只 集 装 箱 的 时 间 由 原 来 的 半 天 缩 短 到 仅 ２ 分 钟 ， 而 成 本 大 大 低 于 国 外 产 品 ， 对 海 关 反 走 私 斗 争 意 义 极 其 重 大 。\n作 为 国 家 科 委 立 项 的 “ 八 五 ” 攻 关 项 目 ， 这 一 系 统 的 实 验 室 研 制 工 作 已 于 １ ９ ９ ６ 年 ２ 月 通 过 国 家 验 收 。\n为 将 这 一 具 有 世 界 水 平 的 科 研 成 果 早 日 转 化 为 实 用 化 的 产 品 ， 清 华 大 学 在 建 立 新 的 成 果 转 化 机 制 方 面 做 了 艰 苦 的 探 索 。\n１ ９ ９ ７ 年 上 半 年 ， 由 清 华 控 股 、 而 体 制 上 完 全 独 立 的 清 华 同 方 公 司 正 式 上 市 。\n集 装 箱 检 测 系 统 的 产 品 化 工 作 由 公 司 正 式 承 担 。\n就 是 在 这 样 的 “ 孵 化 器 ” 中 ， 大 型 集 装 箱 检 测 系 统 的 工 程 化 研 究 与 开 发 进 展 顺 利 ， 解 决 了 多 项 重 大 技 术 难 题 。\n到 目 前 为 止 ， 以 “ 同 方 视 威 ” 命 名 的 检 测 系 统 产 品 化 制 造 定 型 已 经 完 成 ， 并 做 好 了 承 接 工 程 项 目 的 准 备 ， 达 到 了 可 以 投 产 制 造 的 程 度 。\n海 关 方 面 表 示 ， 将 尽 快 启 动 第 一 套 国 产 大 型 集 装 箱 检 测 系 统 的 示 范 工 程 项 目 。\n", "flag": [0, 0, 0, 0, 0, 0, 0, 0, 0, 0, 0, 0, 0, 0, 0, 0, 0, 0, 0, 0, 0, 0, 0, 0, 0, 0, 0, 0, 0, 0, 0, 0, 0, 0, 0, 0, 0, 0, 0, 0, 0, 0, 0, 0, 0, 0, 0, 0, 0, 0, 0, 0, 0, 0, 0, 0, 0, 0, 0, 1, 1, 0, 0, 0, 0, 0, 0, 0, 0, 0, 0, 0, 0, 0, 0, 0, 0, 0, 0, 0, 0, 0, 0]}
{"eventpn": [387, 388], "eventspan": [363, 383], "allspan": [[363, 383]], "id": "733.txt", "doc": "清 华 科 研 成 果 转 化 新 机 制 挂 果 大 型 集 装 箱 检 测 系 统 『 孵 化 』 成 型\n本 报 北 京 １ 月 ７ 日 讯 〓 记 者 杨 健 报 道 ： 经 过 近 两 年 艰 苦 努 力 ， 我 国 第 一 套 国 产 大 型 集 装 箱 检 测 系 统 完 成 了 由 成 果 向 产 品 的 转 化 。\n今 天 ， 该 项 目 的 产 品 化 工 作 在 清 华 大 学 通 过 了 专 家 委 员 会 的 审 定 。\n专 家 们 对 该 校 在 探 索 科 研 成 果 转 化 新 机 制 方 面 取 得 的 这 一 成 绩 给 予 高 度 评 价 。\n大 型 集 装 箱 检 测 系 统 利 用 核 辐 射 扫 描 成 像 技 术 ， 实 现 集 装 箱 免 开 箱 检 测 ， 扫 描 一 只 集 装 箱 的 时 间 由 原 来 的 半 天 缩 短 到 仅 ２ 分 钟 ， 而 成 本 大 大 低 于 国 外 产 品 ， 对 海 关 反 走 私 斗 争 意 义 极 其 重 大 。\n作 为 国 家 科 委 立 项 的 “ 八 五 ” 攻 关 项 目 ， 这 一 系 统 的 实 验 室 研 制 工 作 已 于 １ ９ ９ ６ 年 ２ 月 通 过 国 家 验 收 。\n为 将 这 一 具 有 世 界 水 平 的 科 研 成 果 早 日 转 化 为 实 用 化 的 产 品 ， 清 华 大 学 在 建 立 新 的 成 果 转 化 机 制 方 面 做 了 艰 苦 的 探 索 。\n１ ９ ９ ７ 年 上 半 年 ， 由 清 华 控 股 、 而 体 制 上 完 全 独 立 的 清 华 同 方 公 司 正 式 上 市 。\n集 装 箱 检 测 系 统 的 产 品 化 工 作 由 公 司 正 式 承 担 。\n就 是 在 这 样 的 “ 孵 化 器 ” 中 ， 大 型 集 装 箱 检 测 系 统 的 工 程 化 研 究 与 开 发 进 展 顺 利 ， 解 决 了 多 项 重 大 技 术 难 题 。\n到 目 前 为 止 ， 以 “ 同 方 视 威 ” 命 名 的 检 测 系 统 产 品 化 制 造 定 型 已 经 完 成 ， 并 做 好 了 承 接 工 程 项 目 的 准 备 ， 达 到 了 可 以 投 产 制 造 的 程 度 。\n海 关 方 面 表 示 ， 将 尽 快 启 动 第 一 套 国 产 大 型 集 装 箱 检 测 系 统 的 示 范 工 程 项 目 。\n", "flag": [1]}
{"eventpn": [387, 388], "eventspan": [363, 383], "allspan": [[363, 383]], "id": "733.txt", "doc": "清 华 科 研 成 果 转 化 新 机 制 挂 果 大 型 集 装 箱 检 测 系 统 『 孵 化 』 成 型\n本 报 北 京 １ 月 ７ 日 讯 〓 记 者 杨 健 报 道 ： 经 过 近 两 年 艰 苦 努 力 ， 我 国 第 一 套 国 产 大 型 集 装 箱 检 测 系 统 完 成 了 由 成 果 向 产 品 的 转 化 。\n今 天 ， 该 项 目 的 产 品 化 工 作 在 清 华 大 学 通 过 了 专 家 委 员 会 的 审 定 。\n专 家 们 对 该 校 在 探 索 科 研 成 果 转 化 新 机 制 方 面 取 得 的 这 一 成 绩 给 予 高 度 评 价 。\n大 型 集 装 箱 检 测 系 统 利 用 核 辐 射 扫 描 成 像 技 术 ， 实 现 集 装 箱 免 开 箱 检 测 ， 扫 描 一 只 集 装 箱 的 时 间 由 原 来 的 半 天 缩 短 到 仅 ２ 分 钟 ， 而 成 本 大 大 低 于 国 外 产 品 ， 对 海 关 反 走 私 斗 争 意 义 极 其 重 大 。\n作 为 国 家 科 委 立 项 的 “ 八 五 ” 攻 关 项 目 ， 这 一 系 统 的 实 验 室 研 制 工 作 已 于 １ ９ ９ ６ 年 ２ 月 通 过 国 家 验 收 。\n为 将 这 一 具 有 世 界 水 平 的 科 研 成 果 早 日 转 化 为 实 用 化 的 产 品 ， 清 华 大 学 在 建 立 新 的 成 果 转 化 机 制 方 面 做 了 艰 苦 的 探 索 。\n１ ９ ９ ７ 年 上 半 年 ， 由 清 华 控 股 、 而 体 制 上 完 全 独 立 的 清 华 同 方 公 司 正 式 上 市 。\n集 装 箱 检 测 系 统 的 产 品 化 工 作 由 公 司 正 式 承 担 。\n就 是 在 这 样 的 “ 孵 化 器 ” 中 ， 大 型 集 装 箱 检 测 系 统 的 工 程 化 研 究 与 开 发 进 展 顺 利 ， 解 决 了 多 项 重 大 技 术 难 题 。\n到 目 前 为 止 ， 以 “ 同 方 视 威 ” 命 名 的 检 测 系 统 产 品 化 制 造 定 型 已 经 完 成 ， 并 做 好 了 承 接 工 程 项 目 的 准 备 ， 达 到 了 可 以 投 产 制 造 的 程 度 。\n海 关 方 面 表 示 ， 将 尽 快 启 动 第 一 套 国 产 大 型 集 装 箱 检 测 系 统 的 示 范 工 程 项 目 。\n", "flag": [1]}
